Workbook

Sheet ОБЩЕЕ
E2: кол | F2: сумма | G2: Раб. места | H2: Всего проектов: | I2: Общ сумма | J2: Общ раб места
D3: Реализованные | E3: =SUM(B13,B17,B20,B31,B32,B35,B43,B49,B50,B51,B52,B53,B62,B65,B68,B69,B73,B76,B90,B93,B94,B82,B87,B36,B30,B63,B98,B99,B100,B101,B102,B106,B95) -> 33 | F3: =SUM(K13,K17,K20,K30,K31,K32,K35,K36,K43,K49,K50,K51,K52,K53,K62,K63,K65,K68,K69,K73,K76,K82,K87,K90,K93,K94,K95,K98,K99,K100,K101,K102) -> 110899.94 | G3: =SUM(G13,G17,G20,G30,G36,G49,G50,G51,G52,G53,G62,G63,G68,G73,G76,G82,G87,G90,G93,G94,G95,G98,G99,G100,G101,G102) -> 2231 | H3: =SUM(E3:E7) -> 83 | I3: =SUM(F3:F7) -> 761416.17 | J3: =SUM(G3:G7) -> 12554
D4: Реализуемые (прошли РКС) | E4: =SUM(B15,B16,B19,B25,B26,B37,B40,B47,B48,B54,B55,B56,B71,B72,B91,B88,B85,B83,B81,B79,B74,B70,B67,B24,B44,B58,B42,B64) -> 28 | F4: =SUM(K16,K15,K19,K24,K25,K26,K37,K40,K42,K44,K47,K48,K54,K55,K56,K58,J64,K67,K70,K71,K72,K74,K79,K81,K83,K85,K88,K91) -> 404618.03 | G4: =SUM(G15,G16,G19,G24,G25,G26,G37,G40,G42,G44,G47,G48,G54,G55,G56,G58,G64,G67,G70,G71,G72,G74,G79,G83,G85,G81,G88,G91) -> 8274
D5: Расширение | E5: =SUM(B45,B60) -> 2 | F5: =SUM(K45,K60) -> 3972.2 | G5: =SUM(G60) -> 60
D6: Проблемные | E6: =SUM(B14,B21,B22,B23,B27,B39,B77,B80,B29,B28,B103,B104,B105,B59) -> 14 | F6: =SUM(I14,I22,I23,I21,I27,I39,I77,I80,I103,I104,I105,L59) -> 190415 | G6: =SUM(G14,G21,G22,G23,G27,G39,G77,G80,G103,G104,G104,G105) -> 1079
D7: Прост и исключенные | E7: =SUM(B78,B86,B33,B97,B96,B34) -> 6 | F7: =SUM(K33,K34,K78,K86) -> 51511 | G7: =SUM(G78,G86) -> 910
A10: № | B10: № | C10: Район | D10: Наименование компании | E10: Наименование проекта | F10: Стадия проекта | G10: Раб. Места | H10: Финансирование | I10: Стоимость, млн. тенге | M10: Ввод объекта по РКС | N10: Ввод объекта по факту | O10: Площадь земельного участка, га | P10: Мощность проекта и производительность | Q10: Текущий статус | R10: ФИО руководителя, контакты | S10: Меры господдержки | T10: долгота | U10: широта
H11: Собственные, АКК/БРК, Растениевод, СКО | I11: Всего по РКС | J11: Вне РКС | K11: Актуализир. сумма | L11: в т.ч. заемные
C12: Балхашский район
A13: 1 | B13: 1 | C13: Балхашский район | D13: ТОО «Неокарбон» - реализован, с.Баканас,ул.Сейфуллина №122А | E13: Переработки рисовой шелухи в производство древесноугольных брикетов и углерод-кремнистого композита | F13: Реализован | G13: 50 | I13: 386.8 | K13: =I13 -> 386.8 | M13: 2025 г. | N13: 2025 г. | O13: 0.9936 | P13: Углерод-кремнистый композит 216 тонн | Q13: Проект действует. На сегодня задействованы 9 работников. После достижения мощности будет увеличено до 50 раб.мест. | R13: Усенов Досжан, 87075655767 | S13: Подведение недостающей ИКИ, ЦН ЗУ - Прочие земли.
A14: 2 | B14: 1 | C14: Балхашский район | D14: ТОО «Тайда животноводство», Бакбактинский с/о | E14: Строительство агропромышленного комплекса по производству яиц | F14: Проблемный | G14: 68 | I14: 3120 | K14: =I14 -> 3120 | M14: 2027 г. | N14: 2027 г. | O14: 50 | P14: 100 млн. яиц в год | Q14: ПСД на государственной экспертизе с 28.04,2026 года, еще не получено, так как срок рассмотрения 1,5 месяца. Ориентировочный выход с ГЭ 20.06.2026г. В связи с неактивностью инвестора предлагается вынести на заседание РКС по отзыву ЗУ. | R14: Руководитель - Ян Цинхай, Уаджитова Амина Абдримовна, 87076408018 | S14: ЗУ на 5 лет. ЦН ЗУ - Прочие земли.
A15: 3 | B15: 1 | C15: Балхашский район | D15: ТОО «Баканас рис», Берекенский с/о | E15: Выращивание риса в Алматинской области | F15: Реализуемые | G15: 35 | I15: 600 | K15: =I15 -> 600 | M15: 2027 г. | N15: 2027 г. | O15: 707.6 | P15: от 5 000-7 000 тонн в год | Q15: В рамках реализации проекта выполняются работы по ограждению территории и проведению земляных работ. Приобретена сельскохозяйственная техника, обеспечено водоснабжение участка. В целях апробации технологии произведен посев риса на пробном участке площадью 50 га. Основной объем посевных работ запланирован на следующий год после получения финансирования от инвестора. В текущем году объем инвестиционных вложений составил 78,5 млн тенге. Реализация проекта осуществляется в соответствии с бизнес-планом. | R15: Рахманов Шавкат Бахтибаевич 87778880877, 87006804511 Орал | S15: ЗУ на 5 лет. ЦН ЗУ - Пашня орошаемая.
A16: 4 | B16: 1 | C16: Балхашский район | D16: ТОО «Баканас Байтак Агро» | E16: Строительство комплекса по переработке люцерны, кукурузы и других кормовых сельскохозяйственных культур | F16: Реализуемые | G16: 13 | I16: 869.1 | K16: 869.1 | M16: 2027 г. | O16: 13 | Q16: Получен государственный акт, однако в связи с некорректно указанным целевым назначением земельного участка документ сдан на корректировку. Начаты земельные работы. | S16: нет
A17: 5 | B17: 1 | C17: Балхашский район | D17: ТОО "СЭМ и КО" - реализован | E17: Предприятие мясного животноводства. Приобретение биологических активов в виде племенного КРС, МРС | F17: Реализован | G17: 99 | H17: СКО | K17: 5000 | L17: 5000 | M17: 2026 г. | P17: МРС - 5018 КРС - 6189 | Q17: Скот закуплен, предприятие действует, проблемных вопросов нет | R17: Абуталипова Асель | S17: Кредитов АПК (СКО)
C18: Енбекшиказахский район
A19: 6 | B19: 1 | C19: Енбекшиказахский район | D19: ТОО «Kazakhstan Central Asia Industrial Company., Ltd», Балтабайский с/о | E19: Переработка биологических отходов и производство органических, экологически чистых удобрений животного происхождения | F19: Реализуемые | G19: 30 | I19: 7200 | K19: =I19 -> 7200 | M19: 2026 г. | N19: 2026 г. | O19: 10 | P19: Мясокостная мука – 15 000 тонн, технический жир – 5 000 тонн | Q19: Оборудование из КНР доставлено. В настоящее время проводятся работы по его монтажу и установке. Для выполнения пусконаладочных работ ожидается поставка необходимых кабелей и проводов. Получение акта ввода объекта в эксплуатацию планируется в июле 2026 года. Реализация проекта осуществляется в соответствии с бизнес-планом. | R19: Руководитель - Sun Jinggang, 87762611499 Дуйсен
A20: 7 | B20: 1 | C20: Енбекшиказахский район | D20: ТОО «Qazaq Global Food JV», Тескенсуский с/о - реализован | E20: Строительство завода по переработке фруктов и овощей | F20: Реализован | G20: 128 | I20: 10000 | K20: =I20 -> 10000 | L20: 7000 | M20: 2026 г. | N20: 2026 | O20: 30 | P20: Переработка до 70 -80 тысяч тонн фруктов и овощей в год | Q20: Строительство завершено, оборудование завезено и установлено. Акт ввода в эксплуатацию на стадии оформления. Текущее время проводится работа по поиску поставщиков сырья для переработки. Торжественное открытие завода запланировно на 19.06.2026 г. | R20: 87025552708 Жуматаев Ержан Ерболатович | S20: ЗУ на 5 лет. ЦН ЗУ - Пастбища.
A21: 8 | B21: 1 | C21: Енбекшиказахский район | D21: ТОО «AGROFINANCE», ИЗ «Шелек» | E21: Строительство ультрасовременного фруктохранилища в Алматинской области | F21: Проблемный | G21: 40 | I21: 10500 | K21: =I21 -> 10500 | M21: 2028 г. | O21: 5 | P21: 10 000 тонн | Q21: Проект планируется к реализации на территории ИЗ «Шелек». Начало работ по подведению ИКИ ожидается через 2 месяца, завершение — в 2027 году. Проведены переговоры с инвестором. В настоящее время инвестор находится за границей. Представитель инвестора 30.06.2026 г. связался с работниками УКИЗ договорились о выезде 07.07.2026 г. чтоб рассмотреть предложения по новым ЗУ. Но сегодня так и не приехал, сославшись что выехал за границу, как будет в Алматы выйдет на связь. В связи с неактивностью инвестора предлагается вынести на заседание РКС по отзыву ЗУ. . | R21: 87781075132 Пасков Иван Степанович | S21: Размещение ИЗ «Шелек». ЦН ЗУ - Пастбища.
A22: 9 | B22: 1 | C22: Енбекшиказахский район | D22: TOО «Тепличный агропромышленный комплекс Синтай», Каражотинский с/о | E22: Выращивание в тепличном комплексе томаты, огурцы, перец, листья салатов, с последующей упаковкой для реализации. Комплекс будет состоять из 46 теплиц площадью каждой по 1 га, цех по упаковке, складские помещения, техничесие помещения. | F22: Проблемный | G22: 100 | I22: 3250 | K22: =I22 -> 3250 | M22: 2027 г. | O22: 50 | P22: 1 066 тыс тонн в год | Q22: На СВХ осуществляется таможенное оформление поставленного оборудования (6 экскаваторов) и металлических каркасов для теплиц. Подготовлены документы на изменение целевого назначения земельного участка под промышленное использование. После завершения процедуры планируется его выкуп. Реализация проекта затягивается в связи с разногласиями между инвестором и руководителем ТОО, препятствующими проведению проектных работ. В связи с неактивностью инвестора предлагается вынести на заседание РКС по отзыву ЗУ. | R22: Руководитель - Ибраев Куандык Аулиханович, инвестор - Ян Цинхай, Уаджитова Амина Абдримовна, 87076408018 | S22: ЗУ на 5 лет. ЦН ЗУ - Пастбища.
A23: 10 | B23: 1 | C23: Енбекшиказахский район | D23: ТОО «Батал Агро», Аватский с/о | E23: Производство семян кукурузы родительских форм | F23: Проблемный | G23: 85 | I23: 3500 | K23: =I23 -> 3500 | L23: 1500 | M23: 2027 г. | O23: 94 | P23: До 559 тонн семян | Q23: На полученном земельном участке площадью 94 га были проведены подготовительные работы к посевной кампании. Однако посевная не была осуществлена в связи с выявлением факта двойного правообладания на данный участок. По состоянию на настоящее время материалы обращения находятся на рассмотрении в Управлении полиции Енбекшиказахского района. По результатам рассмотрения в пределах компетенции органом полиции будет принято соответствующее процессуальное решение в порядке и сроки, установленные законодательством Республики Казахстан. | R23: 87773277919 Айдарбаев Берик Ерикович 8 705 265 8870 Елена (бухг) | S23: ЗУ на 49 лет. ЦН ЗУ - Пашня.
A24: 11 | B24: 1 | C24: Енбекшиказахский район | D24: ТОО «Дусан Инжиниринг», Акшиский с/о | E24: Организация МТФ на 1 200 голов КРС | F24: Реализуемые | G24: 50 | I24: 31840 | K24: =I24 -> 31840 | L24: 2400 | M24: 2034 г. | O24: 84 | P24: до 27 тыс. тонн в год | Q24: Приобретен земельный участок площадью 576 га, пробурена скважина. Закуплены две дождевальные установки производства КНР, достигнута договоренность о поставке еще трех установок. Получено АПЗ на систему орошения, ведется работа по оформлению лицензии на недропользование. По проекту МТФ разработана ПСД, получено положительное заключение государственной экспертизы. Приобретены четыре трактора с навесным оборудованием и прицепами, выполнены агротехнические работы, создано 9 рабочих мест. В текущем году планируется перевод 250 га земель на орошаемое земледелие с применением влагосберегающих технологий. Финансирование проекта планируется через АО «АКК». В связи с отсутствием финансирования строительство МТФ перенесено на 2027 год. Проект реализуется поэтапно: создание кормовой базы, строительство МТФ с приобретением маточного поголовья КРС, а также строительство перерабатывающих цехов и расширение поголовья. Объем инвестиций в проект в 2025 году составил 1,2 млрд тенге. Дополнительно в текущем году инвестировано 200 млн тенге. Реализация проекта осуществляется в соответствии с бизнес-планом. | R24: 8 775 224 7474 ЫСҚАҚ ТАЛҒАТ БАТЫРҰЛЫ | S24: ЗУ на 5 лет. ЦН ЗУ - Пастбища.
A25: 12 | B25: 1 | C25: Енбекшиказахский район | D25: ТОО «QazEcoDan», Масакский с/о | E25: Строительство Элеватора -комплекса по приемке, очистке, сушке и хранению зерновых и масленичных культур, производству комбинированных кормов | F25: Реализуемые | G25: 51 | I25: 7975.333 | K25: =I25 -> 7975.333 | M25: 1 этап - 2026 г. 2 этап - 2027 г. | N25: 1 этап - 2026 г. 2 этап - 2027 г. | O25: 9.6 | P25: Очистка, сушка: 40-60 тонн/час Хранение в силосах: 30 тыс. тонн Мощностью производства кормов 120 тонн/сутки | Q25: Строительство I очереди проекта завершено на 98%, акт ввода объекта в эксплуатацию находится на согласовании. Объем инвестиций составил 5,8 млрд тенге. Завершено строительство основных производственных объектов, включая сушильную печь, силосы, ЛЭП-35, газгольдер, железнодорожный тупик и монтаж технологического оборудования. На завершающей стадии находятся работы по объектам вспомогательной инфраструктуры. Для повышения эффективности проекта требуется подключение к природному газу, что позволит снизить себестоимость сушки зерновых культур. Также рассматривается расширение железнодорожного тупика путем строительства трех дополнительных веток. Вопрос строительства газопровода от п. Казтай Ултараков прорабатывается с местными исполнительными органами. | R25: 87716111117 Ерлан руководитель проекта, Руководитель Кайралапин Казбек +7 701 227 0091 | S25: ЗУ на 10 лет. ЦН ЗУ - Пастбища.
A26: 13 | B26: 1 | C26: Енбекшиказахский район | D26: ТОО «Мың жылқы шаруа қожалығы», Масакский с/о Саймасай, Каратурык. | E26: Строительство и организация деятельности конефермы | F26: Реализуемые | G26: 20 | I26: 1576.6 | K26: =I26 -> 1576.6 | M26: 2027 г. | O26: 4457.7 | P26: 1 000 лошадей | Q26: Введутся работы по подготовке к СМР, произведен закуп лошадей в кол-ве 360 голов на 432 млн тенге. На 5 га планируется строительство кошары, навесов, загонов, остальную землю использовать под пастбище. | R26: Руководитель - Оразалин Галымжан Серикович 87011116911 | S26: ЗУ на 5 лет. ЦН ЗУ - Пастбища.
A27: 14 | B27: 1 | C27: Енбекшиказахский район | D27: ТОО «Kasym ASES», Рахатский с/о | E27: Завод по переработке куриных лап | F27: Проблемный | G27: 200 | I27: 1221 | K27: =I27 -> 1221 | M27: 2026 г. | N27: 2027 г. | O27: 3 | P27: 15 000 тонн/год | Q27: Произведена смена целевого назначения земельного участка на промышленное использование, на стадии получения государственного акта. Имеется частичная инфраструктура: получены технические условия по электроснабжению, подведено освещение, водоснабжение обеспечено через скважину, газоснабжение отсутствует, подъездной путь требует отсыпки. В связи с планируемой сменой учредителя (вхождение гражданина Турции с соответствующим опытом и инвестициями) и руководителя ТОО в июле текущего года, работы по подаче заявки на АПЗ не проводились. | R27: Жолдыбай Есентай руководитель и учредитель, представитель Адильбек Аргинбаев 8 778 358 9621 | S27: ЦН ЗУ - пастбища
A28: 15 | B28: 1 | C28: Енбекшиказахский район | D28: ТОО "ПОМОНА" | E28: Строительство и эксплуатация систем влагосберегающих технологий для выращивание кукурузы на зерно | F28: Инвестиционные проекты реализуемые по программе развития растениеводства. | H28: Растениевод | K28: 361.8 | M28: 2026 г. | O28: 250 | P28: 794 тонны в год | Q28: Ранее несоответствующее договору оборудование возвращено поставщику. На текущий момент приобретено новое оборудование, которое находится на складе поставщика. Поставка на объект и завершение монтажных работ запланированы на август 2026 года. Приобретается: Дождевальная машина фронтального типа 2 шт и дождевальная машина кругового действия - 8 шт. | R28: Аяпбергенов Бауржан Болатович
A29: 16 | B29: 1 | C29: Енбекшиказахский район | D29: ТОО "Revival of apples" | E29: Строительство и эксплуатация систем влагосберегающих технологий для выращивание кукурузы на зерно | F29: Инвестиционные проекты реализуемые по программе развития растениеводства. | H29: Растениевод | K29: 520 | M29: 2026 г. | O29: 400 | P29: 1 253 тонн в год | Q29: На площадку реализации проекта поставлена сельскохозяйственная техника, включая разбрасыватели жидкого и твердого навоза, а также кормораздатчики. Ранее несоответствующее договору оборудование возвращено поставщику. Новое оборудование приобретено и находится на складе поставщика, его поставка и монтаж запланированы на август 2026 года. Приобретается: Дождевальная машина фронтального типа 2 шт и дождевальная машина кругового действия - 8 шт. | R29: Молдаш Әсел
A30: 17 | B30: 1 | C30: Енбекшиказахский район | D30: ТОО FRESH FISH KZ | E30: Рыбоводство | F30: Реализуемые | G30: 20 | H30: СКО | K30: 651.3 | L30: 500 | M30: 2026 г. | P30: 1512 тонн рыбы в год | Q30: Конкурсная комиссия одобрило финансирование по программе кредитование в сфере АПК (по опыту СКО) на приобретение оборудования для глубокой переработки форели и других видов рыб: свежей, мороженной, сушеной и копченой рыбы, а также красной икры. | R30: Мурат Аманжол, 87756327171
A31: 18 | B31: 1 | C31: Енбекшиказахский район | D31: КХ «Айдарбаев» - реализован | E31: Расширение молочно товарной фермы | F31: Реализован | H31: СКО | K31: 650 | L31: 650 | M31: 2026 г. | P31: 1270 голов, 6200 тонн в год | Q31: МТФ работает, проблемных вопросов нет | R31: Айдарбаев Ерик Серикович
A32: 19 | B32: 1 | C32: Енбекшиказахский район | D32: ТОО «ABDI AGRO» -- реализован | E32: Строительство молочно товарной фермы | F32: Реализован | H32: СКО | K32: 1314.2 | L32: 1314.2 | M32: 2026 г. | P32: 400 голов, 2000 тонн в год | Q32: МТФ работает, проблемных вопросов нет | R32: Абдиев Ержан Шубаевич 87015558622
A33: 20 | B33: 1 | C33: Енбекшиказахский район | D33: ИП «Тұржан Дәулетхан Мәжитұлы» | E33: Строительство молочно товарной фермы | F33: Простаивающий | H33: СКО | K33: 2000 | L33: 2000 | M33: 2026 г. | P33: 612 голов, 2700 тонн в год | Q33: Строительство МТФ завершено, оборудование доильного зала установлено, ожидается пусконаладка, скот не поставлен, но оплата произведена. В связи с неисполнением обязательств, АО "СПК Конаев" подал исковое заявление о погашении просроченной задолженности. | R33: Маметов Марат
A34: 21 | B34: 1 | C34: Енбекшиказахский район | D34: АО «Агропромышленная компания Адал» - реализован | E34: Современная молочно-товарная ферма | F34: Реализован | H34: СКО | K34: 1833.8 | L34: 1833.8 | M34: 2026 г. | P34: 2371 голов, 11160 тонн в год | Q34: Строительство дополнительного корпуса МТФ и нового доильного зала завершено, монтаж оборудования коровника и доильного зала завершено. | R34: Смаилов Серик
A35: 22 | B35: 1 | C35: Енбекшиказахский район | D35: КХ «Алимжанов» - реализован | E35: Расширение молочно товарной фермы | F35: Реализован | H35: СКО | K35: 199.5 | L35: 199.5 | M35: 2025 г. | P35: 831 голов, 3500 тонн в год | Q35: МТФ работает, проблемных вопросов нет | R35: Алимжанов Тілек
A36: 23 | B36: 1 | C36: Енбекшиказахский район | D36: ТОО «Абди Агро» - реализован | E36: Строительство и эксплуатация систем влагосберегающих технологий | F36: Реализован | G36: 10 | I36: 601.8 | K36: 601.8 | M36: 2026 г. | P36: 400 голов, 2000 тонн в год | Q36: МТФ работает, проблемных вопросов нет | R36: Абдиев Ержан Шубаевич
A37: 24 | B37: 1 | C37: Енбекшиказахский район | D37: ТОО «K&J AGRO» | E37: Строительство теплицы по выращиванию шампиньонов | F37: Реализуемые | G37: 100 | I37: 1500 | K37: 1500 | M37: 2029 г. | O37: 4 | P37: 2 тыс. тонн в год | Q37: Планируется заказ проектно-сметной документации. Ожидает подведения инфраструктуры на ИЗ «Шелек» | R37: Ракыш Темирлан | S37: нет
C38: Жамбылский район
A39: 25 | B39: 1 | C39: Жамбылский район | D39: TOO «DARIA Company», Шолаккаргалинский с/о | E39: Тепличный комплекс | F39: Проблемный | G39: 70 | I39: 15000 | K39: =I39 -> 15000 | L39: 15000 | M39: 2027 г. | O39: 15 | P39: 3 тыс тонн год | Q39: В связи с несоответствием ранее полученных технических условий по электроснабжению и газоснабжению требованиям проекта проводится перепроектирование линии электропередачи (срок завершения — до 15.06.2026 г.). После получения обновлённых решений проект будет направлен на государственную экспертизу. Финансирование планируется через АО «Банк Развития Казахстана» (БРК). Работы в настоящее время не ведутся. В связи с неактивностью инвестора предлагается вынести на заседание РКС по отзыву ЗУ. | R39: Руководитель - Мацыгин Дмитрий Вениаминович, 8 777 229 5000 Маргулан; Акмарал 8 747 701 87 74 | S39: ЗУ на 3 года. ЦН ЗУ - пашня орошаемая
A40: 26 | B40: 1 | C40: Жамбылский район | D40: ТОО «Кок Тениз К», Темиржолский с/о | E40: Расширение мощностей по переработке кукурузы с 10 000 до 50 000 тонн в год | F40: Реализуемые проекты, по линии кредитования АПК по опыту СКО | G40: 10 | H40: СКО | K40: 1800 | L40: 1800 | M40: 2027 г. | P40: 50 тыс тонн в год | Q40: Конкурсная комиссия одобрило финансирование по программе кредитование в сфере АПК (по опыту СКО) на приобретение оборудования для модернизации и расширение действующего производства в сумме 1,8 млрд.тенге. | R40: Кошкинов Ержан Абдулинович +77015396668, 8 706 407 9137 Ерасыл - сын | S40: ЗУ на 10 лет. ЦН ЗУ - пашня богарная
D41: ТОО «Кок Тениз К», Темиржолский с/о | E41: Строительство и эксплуатация систем влагосберегающих технологий | F41: Реализуемые | G41: 10 | I41: 750 | M41: 2027 г. | O41: 3080 | Q41: 15.06.2026 г. планируется доставка трех дождевальных установок для орошения земельных участков общей площадью 200 га. Проводится работа по выбору поставщика дождевальных установок для организации орошения 1 000 га земель, предназначенных под многолетние культуры. Объем инвестиций в проект в текущем году составляет 750 млн тенге. Реализация проекта осуществляется в соответствии с утвержденным бизнес-планом.
A42: 28 | B42: 1 | C42: Жамбылский район | D42: ТОО «Научно производственный центр Генофонд» | E42: Строительство МТФ на 600 голов КРС | F42: Реализуемые | G42: 18 | H42: СКО | K42: 2400 | L42: 1400 | M42: 2027 г. | P42: 600 голов, 5000 тон в год | Q42: Завршение строительствв МТФ планируется в до конца июля месяца текущего года, для приобретения оборудования МТФ, доильного зала, КРС, Конкурсной комиссией утверждено финансирование на 1,4 млрд тенге. Финансирование планируется в текущем месяце. | R42: 8-701 303 5050 Толемисов Махан Кенжегазинович, бухгалтер - 8-701 303 22 88 Кумис Мурзалинова | S42: ПСД на стадии разработки, представлен государственный акт на земельный участок
A43: 29 | B43: 1 | C43: Жамбылский район | D43: ИП Сарсембаева Р.Г. - реализован | E43: Строительство и эксплуатация систем влагосберегающих технологий для выращивание кукурузы на зерно | F43: Реализован | H43: Растениевод | K43: 941 | M43: 2025 г. | N43: 2025 г. | O43: 488 | P43: 2258 тонн в год | Q43: Приобретенное оборудование введено в эксплуатацию, проблемных вопросов нет. Приобретено: Дождевальные машины кругового типа - 9шт.так же система капельного орошения на 180 га. | R43: Абулгазинов Марлен 87011112789
A44: 30 | B44: 1 | C44: Жамбылский район | D44: ТОО «Алматы құс фабрикасы Жетісу» | E44: Разведение птицы на мясо, племенной птицы и молодняка | F44: Реализуемые | G44: 6000 | H44: БРК | K44: 146300 | M44: 2028 г. | P44: 100 тыс тонн | Q44: ТОО «Алматы құс фабрикасы Жетісу», стс-сть 146,3 млрд тенге. Площадь - 5838,4 га. Проблемные вопросы: подведение инфраструктуры. Текущее состояние: ГЭ имеется, ожидается ПСД по инфраструктуре. ПСД по автодорогам и мостам подготовлена. Получено АПЗ и согласован эскизный проект.
A45: 31 | B45: 1 | C45: Жамбылский район | D45: ТОО «Happy Farm» | E45: Строительство молочно товарной фермы | F45: Реализуемые | H45: СКО | K45: 1472.2 | L45: 1472.2 | M45: 2026 г. | P45: 408 голов, 2000 тонн в год | Q45: СМР не завершен, срок завершения строительства планируется на 10.2026 года, скот и оборудование завезено в полном объеме, монтаж доильного зала завершен, начаты пусконаладачные работы. | R45: Маметов Марат
C46: Илийский район
A47: 32 | B47: 1 | C47: Илийский район | D47: ТОО «Компания «Сары Булак», Аксайский с/о, село Аксай уч.1531 | E47: По переработке куриного помёта в органические удобрения | F47: Реализуемые | G47: 60 | I47: 550 | K47: =I47 -> 550 | M47: 2026 г. | N47: 2027 г. | O47: 6 | P47: Переработка куриного помёта – 200 тонн в сутки | Q47: Лагуны для хранения и переработки птичьего помета выполнены и забетонированы. Вопрос получения технических условий от АЖК остается нерешенным. Проведена повторная встреча с руководством АЖК, достигнута договоренность о повторной подаче документов на получение ТУ. Оборудование закуплено и находится на складах без монтажа и ввода в эксплуатацию. Получение акта ввода объекта в эксплуатацию планируется в 2027 году. | R47: 87012281400 Берик Меирханович | S47: ЦН ЗУ - пастбище
A48: 33 | B48: 1 | C48: Илийский район | D48: ТОО «Alfalfa», Аксайский с/о | E48: Выращивание люцерны | F48: Реализуемые | G48: 30 | H48: СКО | I48: 5000 | K48: =I48 -> 5000 | L48: 1500 | M48: 2026 г. | O48: 1700 | P48: Тюкованная люцерна 12 000 тонн/год, гранулированная люцерна 8 000 тонн в год | Q48: Получено финансирование от АО «СПК Конаев» в размере 1,5 млрд тенге. На стадии завершения строительно-монтажные работы по внутренним сетям водоснабжения. Поставлены 8 дождевальных установок, не введены в эксплуатацию, 3 установки находятся в пути. В текущем году будут установленны 11 дождевальных машин покрывающих 700 га земли, в 2027 году планируется приобретение и установка дождевальных машин покрывающих оставшиеся 1000 га. Осуществляется поиск инвестора/инвестиций для строительства наружных сетей водоснабжения, проводится расчет окупаемости проекта. | R48: Руководитель - Яний Сергей Владимирович, Ауельбек 87017444703 | S48: Подведение недостающей ИКИ, ЦН ЗУ - пастбище
A49: 34 | B49: 1 | C49: Илийский район | D49: АО "Каскеленское" - реализован | E49: Строительство и эксплуатация систем влагосберегающих технологий для выращивание кукурузы на зерно | F49: Реализован | G49: 20 | H49: Растениевод | K49: 386 | M49: 2026 г. | O49: 5882 (на 86 га ставится капельное орошение) | P49: 930 тонн в год | Q49: Приобретенное оборудование капельного орошения введено в эксплуатацию, сельхоз техника (кормоуборочные комбайны 2шт) доставлено на место реализации проекта, проблемных вопросов нет
A50: 35 | B50: 1 | C50: Илийский район | D50: ТОО Каргалы Крахмал - реализован | E50: Строительство и эксплуатация систем влагосберегающих технологий для выращивания кукурузы на зерно | F50: Реализован | G50: 10 | H50: Растениевод | K50: 142 | M50: 2025 г. | O50: 416 (на 160 га ставится капельное орошение) | P50: 343 тонн в год | Q50: Приобретенное оборудование введено в эксплуатацию, проблемных вопросов нет
A51: 36 | B51: 1 | C51: Илийский район | D51: ТОО «Научно производственный центр Генофонд» - реализован | E51: Расширение молочно товарной фермы | F51: Реализован | G51: 19 | H51: СКО | K51: 553.6 | L51: 553.6 | M51: 2025 г. | O51: 1162 | P51: 1800 голов, 7440 тонн в год | Q51: МТФ работает, проблемных вопросов нет | R51: Толемисов Махан
A52: 37 | B52: 1 | C52: Илийский район | D52: ТОО «Ризык Агро» - реализован | E52: Расширение молочно товарной фермы | F52: Реализован | G52: 23 | H52: СКО | K52: 1209.8 | L52: 1209.8 | M52: 2025 г. | O52: 5400 | P52: 629 голов, 3100 тонн в год | Q52: МТФ работает, проблемных вопросов нет | R52: Абулгазинов Марлен
A53: 38 | B53: 1 | C53: Илийский район | D53: ТОО «Ак сут LLC» - реализован | E53: Расширение молочно товарной фермы | F53: Реализован | G53: 50 | H53: СКО | K53: 300.7 | L53: 300.7 | M53: 2025 г. | O53: 184 | P53: 2592 голов, 6900 тонн в год | Q53: МТФ работает, проблемных вопросов нет | R53: Сембай Елжас
A54: 39 | B54: 1 | C54: Илийский район | D54: ТОО «LUX Grand Park» | E54: Строительство молочно-товарной фермы в Илийском районе Алматинской области | F54: Реализуемые | G54: 100 | I54: 650 | K54: 650 | M54: 2027 г. | O54: 282 | P54: 876 000 литров натурального молока в год | Q54: Получили выписку РКС | S54: нет
A55: 40 | B55: 1 | C55: Илийский район | D55: ТОО «Агрофирма Dinara-Ranch» | E55: Растениеводство на орошаемых землях для создание кормовой базы КРС | F55: Реализуемые | G55: 18 | I55: 700 | K55: 700 | M55: 2028 г. | O55: 390.2 | P55: 6 248 т. кормов в год | Q55: Начаты посевные работы
A56: 41 | B56: 1 | C56: Илийский район | D56: АО «АЛЕЛЬ АГРО» | E56: Строительство завода по переработке отходов птицеводства (производство кормовых добавок из пера, кишок, крови, падежа) | F56: Реализуемые | G56: 27 | I56: 670 | K56: 670 | M56: 2027 г. | O56: 3.2 | P56: 1.Линия переработки крови (4.5 т/день)2.Линия переработки кишок (9т/день)3. Линия переработки пера (9т/день) | Q56: Получили выписку от РКС | S56: нет
C57: Карасайский район
A58: 42 | B58: 1 | C58: Карасайский район | D58: ТОО «Жигалма» (Caspian Beverage Holdings), Жамбылский с/о | E58: Производство безалкогольных напитков и минеральных вод | F58: Реализуемые | G58: 250 | I58: 15800 | K58: =I58 -> 15800 | L58: 5000 | M58: 2027 г. | N58: 2027 г. | O58: 10 | P58: 500 млн. литров продукции в год, 120 млн. единиц упаковки в год | Q58: Заявление на получение архитектурно-планировочного задания (АПЗ) направлено. Подана заявка в АЖК на ТУ -2 МВ (врменная). 24.04.2026 года получено официальное письмо от АЖК, согласно которому запланированы работы по увеличению мощности на подстанции «Чемолган», к которой будет осуществлено подключение объекта компании. Осуществляется поиск инвестора/инвестиций. | R58: Руководитель - Ахметов Алмат Сагындык улы, 87777799078, Рустам Давлетов +7 (777) 779 90 78 | S58: ЗУ на 3 года. ЦН ЗУ - пашня орошаемая
A59: 43 | B59: 1 | C59: Карасайский район | D59: СПК «Жетысу» | E59: Молочно товарная ферма | F59: Проблемный | H59: СКО | K59: 994 | L59: 994 | M59: 2026 г. | Q59: Заемщику неоднократно разъяснялась необходимость своевременного освоения заемных средств. 17 июля 2025 года заключен договор с ТОО «PANAGRO SERVICE» на приобретение доильно-молочного блока с доильным залом стоимостью 374 000 000 тенге, оплата произведена 21 июля 2025 года. 30 июля 2025 года прокуратурой Алматинской области внесено представление в связи с нецелевым использованием займа и размещением средств на депозитных счетах. В результате проведенной Поверенным (агентом) работы 25 сентября 2025 года СПК «Жетысу» возвратило часть займа в размере 620 102 785 тенге. По оставшейся сумме займа (374 000 000 тенге) и взысканию штрафа Поверенным (агентом) подан иск в суд. Решением суда первой инстанции от 26 декабря 2025 года с СПК «Жетысу» взысканы сумма займа и штраф в размере 248 525 696 тенге. 17 марта 2026 года апелляционная инстанция отменила данное решение. 2 апреля 2026 года подана кассационная жалоба. Ожидается назначение судебного заседания. | R59: Исагулов Жанат
A60: 44 | B60: 1 | C60: Карасайский район | D60: АО "АзияАгроФуд" | E60: Глубокая переработка по переработке сельскохозяйственной продукции. Приобретение оборудования. | F60: Реализуемые проекты, по линии кредитования АПК по опыту СКО | G60: 60 | H60: СКО | K60: 2500 | L60: 2500 | M60: 2026 г. | P60: 110 тыс тонн в год | Q60: Произведена предоплата за изготовление оборудования в размере 60% от суммы контрактов. Срок поставки оборудования по контракту август 2026 года. Начало монтажа приобретенного оборудования запланирована на сентябрь 2026 года. | R60: Ашенов Саян | S60: Кредитов АПК (СКО)
C61: Талгарский район
A62: 45 | B62: 1 | C62: Талгарский район | D62: СПК «Племзавод «Алматы» - реализован, участок Малайсары. | E62: Развитие овцеводства породы Иль-Де-Франс в Жетысу | F62: Реализован | G62: 100 | I62: 750 | K62: 1500 | L62: 0 | M62: 2025 г. | O62: 2512 | P62: 1000 голов, 200 тонн мяса в год | Q62: Проект реализован. Ведутся селекционные работы: из г. Минск завезено 100 голов баранов-производителей породы Иль-де-Франс, сформировано маточное стадо численностью 1 500 голов. На площади 680 га проводятся работы по переводу земель в категорию орошаемых для внедрения влагосберегающих технологий. Получены технические условия на подключение к электрическим сетям, проектно-сметная документация прошла государственную экспертизу. В настоящее время осуществляется приобретение дождевальных (фрегатных) установок, монтаж которых запланирован на осень текущего года. | R62: Ахметжанов Рустем Кажиканович, 87775146500 | S62: ЗУ на 49 лет. ЦН ЗУ - 528 га-орошаемая пашня, 1 984 га- пастбище.
A63: 46 | B63: 1 | C63: Талгарский район | D63: ТОО COFCO TRANS Бин 250640019716 | E63: Элеватор по производству кормовой муки | F63: Реализован | G63: 23 | H63: собственные средства | K63: 5500 | M63: 2026 г. | P63: 293 тыс тонн | Q63: На сегодняшний день строительно-монтажные работы выполнены на 75 %. Работы ведутся в соответствии с утвержденным графиком. Завершение проекта планируется в течение ближайших двух месяцев. В настоящее время на объекте продолжаются основные строительные и организационные мероприятия, направленные на своевременное завершение всех предусмотренных этапов работ. С учетом текущих темпов реализации проекта, полный ввод объекта в эксплуатацию ожидается до начала уборочной кампании урожая.
A64: 47 | B64: 1 | C64: Талгарский район | D64: ТОО "ALATAU GREEN PRODUCTION" | E64: Строительство мультикультурного тепличного комплекса на 8 гектар | F64: Реализуемые | G64: 400 | H64: БРК | J64: 17300 | L64: 13408.8 | M64: 2025-2028 г. | O64: 8 | P64: 4 тыс тонн | Q64: Общая стоимость проекта составляет 17,3 млрд тенге. Финансирование осуществляется за счет собственных средств компании и кредита АО «Банк Развития Казахстана». Получены АПЗ и технические условия на подключение к инженерным сетям. Разрешение на строительство мостового перехода через Большой Алматинский канал получено. Проектно-сметная документация находится на завершающей стадии. Проект предусматривает создание 400 постоянных рабочих мест. Ввод объекта в эксплуатацию планируется до конца III квартала 2026 года, выход на полную проектную мощность — в 2027 году.
A65: 48 | B65: 1 | C65: Талгарский район | D65: ТОО «Байсерке Агро» - реализован | E65: Расширение молочно товарной фермы | F65: Реализован | H65: СКО | K65: 500 | L65: 500 | M65: 2025 г. | P65: 1125 голов, 4650 тонн в год | Q65: МТФ работает, проблемных вопросов нет | R65: Жунисбеков Галыжан
C66: Уйгурский район
A67: 49 | B67: 1 | C67: Уйгурский район | D67: ТОО «Rancho Hampshire», Малодиханский с/о | E67: Организация производственной базы сельхозназначения (Разведение английской породы овец Гемпшир и выращивание кукурузы, люцерны и разнотравья) | F67: Реализуемые | G67: 50 | I67: 1000 | K67: 1000 | M67: 1 этап 2026 г. 2 этап 2028 г. | N67: 1 этап 2026 г. 2 этап 2028 г. | O67: 1500 | P67: Проектная мощность на 2000 голов, факт более 400 голов | Q67: Текущее сосотояние: Проект находится на стадии реализации. Степень готовности – 50 %. Проблемные вопросы: ТОО зарегистрировано в Илийском районе. | R67: Директор - Чепис Сергей +7 701 555 22 28 | S67: ЗУ на 10 лет. ЦН ЗУ - пастбище.
A68: 50 | B68: 1 | C68: Уйгурский район | D68: ТОО "Eco Park Tour" - реализован | E68: Строительство и эксплуатация систем влагосберегающих технологий длч сада по выращиванию яблок и абрикоса | F68: Реализован | G68: 10 | H68: Растениевод | J68: 217 | K68: 217 | M68: 2026 г. | N68: 2026 г. | O68: на 180 га ставится капельное орошение | P68: 537 тонн в год | Q68: Реализованный проект | R68: Абдулминов Бахтияр Баратович | S68: 1,01 га
A69: 51 | B69: 1 | C69: Уйгурский район | D69: ТОО Kolzhat Agro - реализован | E69: Строительство и эксплуатация систем влагосберегающих технологий для выращивания люцерны | F69: Реализован | H69: Растениевод | K69: 527.237 | M69: 2026 г. | O69: 1490 (на 297 га ставяться дождевальные системы) | P69: 1249 тонн люцерны с 1490 га | Q69: Приобретены дождевальные машины в кол-ве 5 шт, система мобильного капельного орошения 2 шт., оборудование введено в эксплуатацию, проблемных вопросов нет. | R69: Нимилостев Петр Петрович
A70: 52 | B70: 1 | C70: Уйгурский район | D70: ТОО «Харвест Агро Холдинг» | E70: Создание агро-индустриального кластера «Harvest» в Уйгурском районе | F70: Реализуемые | G70: 60 | I70: 18200 | K70: 18200 | M70: 2029 г. | O70: 100 | P70: до 50 тыс. тонн кукурузы и 15 тыс. тонн сои в год | Q70: 30.01.2026 года состоялось заседание земельной комиссии, по итогам которого одобрено предоставление ЗУ площадью 3 000 га сроком на 10 лет из запрошенных 10 000 га на 49 лет. 27.03.2026 года проведены общественные слушания, где было одобрено выдача еще 2 000 га.
A71: 53 | B71: 1 | C71: Уйгурский район | D71: ТОО «Harvesto Logistics» | E71: Строительство завода по производству семян гибридов кукурузы и подработке, хранению товарного зерна | F71: Реализуемые | G71: 70 | I71: 3600 | K71: 3600 | M71: 2028 г. | O71: 100 | P71: до 108 тыс. тонн хранения с суточной переработкой до 1 200 тонн в сезон. | Q71: На стадии прохождения земельной комиссии | R71: Мурат Амангельдиевич | S71: нет
A72: 54 | B72: 1 | C72: Уйгурский район | D72: ТОО «Kaz Corn» | E72: Освоение залежных земель для возделывания гибридов кукурузы и родительских форм путем внедрения водосберегающих технологий | F72: Реализуемые | G72: 35 | I72: 8500 | K72: 8500 | M72: 2027 г. | O72: 5000 | P72: 4 000 га товарной кукурузы, 1 000 га семеноводство | Q72: На стадии прохождения земельной комиссии | R72: Мурат Амангельдиевич | S72: нет
A73: 55 | B73: 1 | C73: Уйгурский район | D73: ТОО «Асем калжат» | F73: Реализован | G73: 180 | I73: 7500 | K73: 7500
A74: 56 | B74: 1 | C74: Уйгурский район | D74: Прима-Кус | E74: Строительство птицеводческого комплекса замкнутого цикла по производству и переработке мяса бройлера | F74: Реализуемые | G74: 140 | I74: 24477 | K74: 24477 | M74: 2028 г. | O74: 542 | Q74: ТОО «Прима Құс» — птицефабрика,строительство 3-й этап. Общая потребность в инвестициях составляет 13 500,0 млн тенге, финансирование проекта обеспечено в полном объеме. На текущий момент строительно-монтажные работы выполнены на 97,1%. Ввод объекта в эксплуатацию запланирован на декабрь 2026 года. После выхода на проектную мощность объем производства будет увеличен до 36 000 тонн мяса птицы в живом весе в год.
C75: г.Конаев
A76: 57 | B76: 1 | C76: г.Конаев | D76: ТОО «Оспанова Девелопмент» - реализован. | E76: Строительство рыбопромышленного комплекса | F76: Реализован | G76: 500 | I76: 9800 | K76: 9800 | L76: 300 | M76: 2023 г. | O76: 27 | P76: 1 тыс. тонн рыбы в год | Q76: Первый этап проекта реализован и введен в эксплуатацию в октябре 2023 года. В настоящее время осуществляется выращивание форели и беррамунди (морского окуня). От реализации последующих этапов проекта, предусматривавших выращивание карпа, инвестор отказался в связи с экономической нерентабельностью. Согласно Правилам субсидирования инвестиционных вложений, сумма возмещения затрат по первому этапу составила 90 млн тенге, что соответствует лишь 0,85 % от стоимости первого этапа проекта. | R76: Бектемисов Максим Сакенович | S76: Подведение недостающей инфраструктуры ЦН ЗУ - прочие земли
A77: 58 | B77: 1 | C77: г.Конаев | D77: ТОО «AXIS Holding», Шенгельдинский с/о, уч. кв. 254 (уч.364 А) | E77: Строительство МТФ на 12 000 КРС, дойное стадо 6 000 КРС. Также строительство цехов по переработке молока и выпуску молочной продукции. | F77: Проблемный | G77: 400 | I77: 121580 | K77: 121580 | M77: 2030 г. | O77: 1340 | P77: 55 тыс.тонн в год | Q77: По факту земельный участок был получен в январе текущего года, после чего начались работы по подготовке проектной документации. Ориентировочный срок завершения разработки проекта — конец июля текущего года. Вместе с тем в ходе отбора и анализа проб воды были получены результаты, свидетельствующие о повышенном содержании солей. Использование такой воды может привести к снижению удоев молока, а также потребует строительства системы водоочистки, что влечет за собой удорожание проекта. В настоящее время рассматривается вопрос о выделении дополнительного земельного участка площадью 1000 кв. м вблизи Капшагайского водохранилища для обеспечения возможности использования воды из данного источника. В связи с изложенным сроки завершения подготовки проектной документации могут быть перенесены. | R77: Василий Филимонов +49 162 7018421 | S77: ЗУ на 3 года. ЦН ЗУ - прочие земли
A78: 59 | B78: 1 | C78: г.Конаев | D78: ТОО «Sofood Kaz» | E78: Строительство завода по производству сыра | F78: Реализуемые | G78: 460 | I78: 35291 | K78: 35291 | L78: 28233 | M78: 2027 г. | O78: 31.8 | P78: 100 тонн в день | Q78: Завершается ограждение ЗУ - 31 га по всему периметру. На период СМР временно подключены э/э, водоснабжения, завершён монтаж временного дорожного покрытия. Ведется СМР складских помещений на 10 тыс кв.м, (ввод 10.2026г.). Подведение инженерной и коммунальной инфраструктуры (ИКИ) планируется за счет местного бюджета. Бюджетная заявка будет вынесена на очередное уточнение бюджета. В настоящее время разрабатывается проектно-сметная документация, ориентировочные сроки получения ПСД первая декада июля и получение государственной экспертизы вторая декада сентября,так как ориентировочные сроки гос. экспертизы 45 дней. В связи с чем, окончательная стоимость будет определена после её завершения. | R78: Аманкосов Курмангали Жандосович 87021324043 , Рауан +7 (707) 837 09 11 | S78: ЗУ на 3 года. ЦН ЗУ - прочие земли
A79: 60 | B79: 1 | C79: г.Конаев | D79: ТОО «Asian International Trading Company», Шенгельдинский с/о, участок Кербулак | E79: Строительство завода по производству комбикорма из плющенной кукурузы | F79: Реализуемые | G79: 158 | I79: 2110 | K79: 2110 | M79: 2029 г. | O79: 20 | P79: 150,0 тыс тонн в год | Q79: Работы по проекту в настоящее время не ведутся. Проект реализуется на территории, прилегающей к СЭЗ «Конаев». Руководитель компании находится в КНР и планирует прибыть в конце июня – начале июля текущего года. В связи с неактивностью инвестора предлагается вынести на заседание РКС по отзыву ЗУ. | R79: Лань Сяо Янь, 87055302473, Кристина 8 (706) 410 10 98 | S79: ЗУ на 1 год. ЦН ЗУ - прочие земли
A80: 61 | B80: 1 | C80: г. Конаев | D80: ТОО «KazGelatin» | E80: Строительство завода по производству пищевого желатина | F80: Проблемный | G80: 100 | I80: 29900 | K80: 29900 | M80: 2027 г. | O80: 44.6 | P80: 10 тыс. тонн | Q80: Ведутся работы по поиску ЗУ для наносной станции | S80: нет
A81: 62 | B81: 1 | C81: г.Конаев | D81: ТОО «Smart Adam Agro» | E81: Выращивание прочих многолетних культур | F81: Реализуемые | G81: 19 | I81: 1200 | K81: 1200 | O81: 900 | P81: Выращивание и производство кормов 5 тыс. тонн / год | R81: Ибекеев Ержан Сембекулы
A82: 63 | B82: 1 | C82: г.Конаев | D82: ТОО «Қапшагай бидай өнімдері» | F82: Реализован | G82: 350 | I82: 12000 | K82: 12000
A83: 64 | B83: 1 | C83: г.Конаев | D83: TOO «Arbo Volt» | E83: Строительство питомника с производственной базы | F83: Реализуемые | G83: 100 | I83: 2400 | K83: 2400 | M83: 2028 г. | O83: 109 | P83: 16 000 саженцев Paulownia Tomentosa | Q83: Получен гос акт. Начали разработку плана детальной планировки. Разработку ПДП планируется завершить в августе 2026 года. . | S83: нет
C84: г.Алатау
A85: 65 | B85: 1 | C85: г.Алатау | D85: ТОО «Молочная Долина», | E85: Строительство МТФ на 1200 голов | F85: Реализуемые | G85: 100 | I85: 18700 | K85: 18700 | L85: 15000 | M85: 2028 г. | O85: 1300 | P85: 13,5 тыс. тонн в год | Q85: Проект готовится к направлению на ГЭ. На поливных ЗУ посеяно 250 га люцерны, кукурузы на корма. Вопрос частичного финансирования рассматривается АО "СПК Конаев". 03.06.2026г. при рассмотрении проект на Комиссии проект был направлен на доработку, так как отсутствовало ПСД и другие документы, разрезающие строительство МТФ на территории города Алатау. | R85: Разумовский Дмитрий Михайлович +7 705 677 9447 dmitriy.r.kz@icloud.com | S85: ЗУ на 49 лет. ЦН ЗУ - пастбище.
A86: 66 | B86: 1 | C86: г.Алатау | D86: ТОО «Zhetysu Koy», | E86: Строительство мясокомбината по докорму, убою и глубокой переработке МРС | F86: Простаивающий | G86: 450 | I86: 12386.2 | K86: 12386.2 | M86: 2027 г. | N86: 2029 г. | O86: 24 | P86: Баранина: 15 т.тн в год-1 этап; 30 т.тн в год - 2 этап | Q86: Проект строительства мясокомбината разработан и готов к реализации, однако его реализация приостановлена до решения вопроса обеспечения объекта канализационной инфраструктурой. По информации инвестора, ранее был разработан и получен положительный результат ГЭ проекта КОС для земельного участка площадью 70 га, который впоследствии был сокращен до 24 га. Вопрос строительства канализационной системы до настоящего времени не решен и является основным сдерживающим фактором проекта. После получения подтверждения о строительстве канализационной инфраструктуры и сроках ее ввода проект будет возобновлен. Финансовые ресурсы для реализации проекта имеются. В связи с неактивностью инвестора предлагается вынести на заседание РКС по отзыву ЗУ. | R86: Плотников Олег Геннадьевич +7 701 722 3319 | S86: Подведение недостающей ИКИ. ЦН ЗУ - пастбище.
A87: 67 | B87: 1 | C87: г.Алатау | D87: ТОО «ФрутАрт» | F87: Реализован | G87: 247 | I87: 42800 | K87: 42800
A88: 68 | B88: 1 | C88: г.Алатау | D88: ТОО «ПепсиКо ЦА» | E88: Завод по производству соленых закусок | F88: Реализуемые | G88: 300 | I88: 81000 | K88: =I88 -> 81000 | L88: 71000 | M88: 2026 г. | N88: 2026 г. | O88: 26.47 | P88: 21 тыс. тонн продукта (чипсы Lay's) | Q88: Ведутся СМР | R88: Маргулан +7 701 722 2727 | S88: ЗУ на 4 года 11 мес. ЦН ЗУ - 15,0га- пашня орошаемая, 11,5 га - пастбища
C89: Райымбекский район
A90: 69 | B90: 1 | C90: Райымбекский район | D90: ТОО "Сарыбастау - ББ" - реализован | E90: Строительство и эксплуатация систем влагосберегающих технологий для выращивания картофеля | F90: Реализован | G90: 10 | H90: Растениевод | K90: 407 | M90: 2025 г. | O90: 200 (на 150 га установлены дождевальные системы) | P90: 1500 тонн картофеля | Q90: В текущем году освоено 169 га из запланированных 200 га. На площади 50 га произведён посев картофеля, на 110 га — ячменя. РКС не проходили. Приобретены 2 дождевальные системы кругового действия. | S90: нет
A91: 70 | B91: 1 | C91: Райымбекский район | D91: ТОО «QARASAZ MILK» | E91: Производственное предприятие по переработке шкур | F91: Реализуемые | G91: 30 | I91: 700 | K91: 700 | M91: 2027 г. | O91: 13 | P91: Переработка шкур КРС и МРС – порядка 10 000 штук в год. | Q91: На стадии оформления земельного участка | R91: Алиева Дамира Нурболовна +7 777 777 1788 | S91: З/У
C92: Кегенский район
A93: 71 | B93: 1 | C93: Кегенский район | D93: СПК «Талас» - реализован | E93: Расширение молочно-товарной фермы | F93: Реализован | G93: 50 | H93: СКО | I93: 492 | K93: 492 | L93: 492 | M93: 2025 г. | O93: 745 | P93: 422 голов, 1375 тонн в год | Q93: Ведутся СМР по расширению. МТФ работает, проблемных вопросов нет | R93: Жамбаев Жусип Ахметказиевич 87010813468. | S93: З/У
A94: 72 | B94: 1 | C94: Кегенский район | D94: ТОО «KeгeнMяcПpoм» | E94: Мясокомбинат с предубойным откормочным комплексом | F94: Реализован | G94: 50 | I94: 2700 | K94: 2700 | M94: 2025 г. | N94: 2025 г. | O94: 380 | P94: 10 тонн мяса в сутки | Q94: Все оборудование на площадке для убоя скота прошло полную проверку. На объект строительства выдан технический паспорт (техпаспорт). | R94: Баймолдаев Токтар Аскарович +7 701 311 1151 | S94: З/У
A95: 73 | B95: 1 | C95: Кегенский район | D95: Производство тонкой шерсти ТОО «MERGEN HOLDING» | E95: Строительство производственной базы по переработке шерсти «MERGEN HOLDING» | F95: Реализуемые | G95: 200 | H95: собственные средства | K95: 1500 | M95: 12.2026 г. | P95: 2 тыс тонн | Q95: Наличие земельного участка; наличие ПСД (АПЗ, рабочий проект, эскизный проект, заключение); Активно ведутся СМР, выполняется комплекс земляных работ, включая разработку и подготовку грунта. Параллельно осуществляются бетонные работы по устройству основных конструктивных элементов. Ведётся монтаж металлоконструкций в соответствии с утверждённой ПСД
A96: 74 | B96: 1 | D96: ТОО «BELES AGRO KZ» | F96: Простаивающий
A97: 75 | B97: 1 | D97: ТОО «AGRO Bionics» | F97: Простаивающий
A98: 76 | B98: 1 | C98: Карасайский район | D98: ИП «Baitelov» | E98: Расширение садкового рыбоводного хозяйства по выращиванию ценных видов рыб с объемом 120 тонн в год | F98: Реализован | G98: 6 | H98: собственные средства | I98: 120 | K98: 120 | M98: 2025 г. | P98: 120 тонн форели в год | Q98: Рыбоводное хозяйство расположен на земельном участке площадью 33,5 га. Для выращивания молоди рыбы имеются 5 естественных прудов общей площадью 2326,4 м кв., которые предназначены для выращивания мальков форели до товарной массы. Пруды оборудованы садками общей площадью 7861 м3 оснащены магистральными каналами водоподачи и дренажной системой. Водоснабжение производится из артезианской скважины с температурным режимом 13-16°С. Рыбоводное хозяйство оснащен необходимой инфраструктурой и оборудованием включая склад для хранения кормов площадью 0,5 м2. Малька форели карпа закупают от местных производителей.
A99: 77 | B99: 1 | C99: Кегенский район | D99: Командитное товарищество «Great Steppe Heritage» | E99: Расширение и автоматизация садковой линии | F99: Реализован | G99: 28 | H99: собственные средства | I99: 2050 | K99: 2050 | L99: 1650 | M99: 2025 г. | P99: 500 тонн форели в год | Q99: Договор с ТОО «Мойнакская ГЭС» на 10 лет по аренде водной глади для установки садков подписан. Установлены 12 садков диаметром 22 м. Провел работу по зарыблению в количестве 250 тыс. штук мальками форели средней массой 12 гр. Корма используются импортные – ALLER AQUA. Кроме того, 2025 году планируется расширение и автоматизация садковой линии. | R99: Байзаков Нурлан диретор 87017557507 Байкен Бекетаевич 87028216346
A100: 78 | B100: 1 | C100: Енбекшиказахский район | D100: ТОО «TogizBulaq» | E100: Создание прудового рыбоводного хозяйства по выращиванию ценных видов рыб с объемом 360 тонн в год | F100: Реализован | G100: 21 | H100: собственные средства | I100: 200 | K100: 200 | M100: 2025 г. | P100: 360 тонн форели в год | Q100: В мае 2022 года начато строительство рыбоводного комплекса на земельном участке площадью 75 гектаров. Проектно-сметная документация прошла государственную экспертизу. Проведена работа по установке оборудования (бассейны, инкубационные аппараты). Запуск 1 этапа выращивание форели начато в начале 2024 года. Проделано 50% работы.
A101: 79 | B101: 1 | C101: Енбекшиказахский район | D101: ТОО "АгроАкваКомплекс" | E101: Расширение прудового рыбоводного хозяйства по выращиванию ценных видов рыб с объемом 279 тонн в год | F101: Реализован | G101: 14 | H101: заемные средства | I101: 300 | K101: 300 | M101: 2025 г. | P101: 279 тонн карп.форели | Q101: имеется 7 прудов, планируется увеличить до 20
A102: 80 | B102: 1 | C102: Жамбылский район | D102: ТОО " ТехноСнаб 2002" | E102: Создание УЗВ Рыбопромышленный комплекс по выращиванию форели и осетра | F102: Реализован | G102: 13 | H102: собственные средства | I102: 450 | K102: 450 | M102: 2025 г. | P102: 150-200 форель и осетра | Q102: Ввод в эксплуатацию в августе 2025 г.
A103: 81 | B103: 1 | C103: Талгарский район | D103: ИП Гульмир | E103: Создание УЗВ | F103: Проблемный | G103: 6 | H103: собственные средства | I103: 350 | K103: 350 | M103: 2025 г. | P103: 80 тонн форели | Q103: 1. На сегодняшний день в рамках проекта по выращиванию форели установлено 6 бассейнов объёмом по 3 тонны каждый, проведено зарыбление рыбопосадочным материалом форели, осуществляется инкубация. На участке имеется пруд, используемый для выращивания рыбы. Ведётся строительство 6 бассейнов под открытым небом ёмкостью по 4 тонны каждый. 2. К хозяйству подведено электроснабжение, функционирует собственная подстанция, обеспечивающая стабильную работу оборудования. 3. Степень готовности проекта составляет около 80% от общего объёма строительно-монтажных работ. Параллельно осуществляется оформление всех необходимых документов и разрешений для полного запуска производства и реализации продукции. 4. Проект реализуется за счёт собственных средств инициатора — индивидуального предпринимателя «Гульмир». На текущий момент инвестировано 250 млн тенге. Для выхода на полную производственную мощность планируется подача заявки на льготный кредит в размере 100 млн тенге под 2,5% годовых. Нужны средства в размере 100 млн. тенге для полного запуска производства
...

Sheet Реализованные
D2: кол | E2: сумма | F2: Раб. места
C3: Реализованные | D3: 33 | E3: 110899.94 | F3: 2231
A5: № | B5: № | C5: Район | D5: Наименование компании | E5: Наименование проекта | F5: Стадия проекта | G5: Раб. Места | H5: Финансирование | I5: Стоимость, млн. тенге | M5: Ввод объекта по РКС | N5: Ввод объекта по факту | O5: Площадь земельного участка, га | P5: Мощность проекта и производительность | Q5: Текущий статус | R5: ФИО руководителя, контакты | S5: Меры господдержки
H6: Собственные, АКК/БРК, Растениевод, СКО | I6: Всего по РКС | J6: Вне РКС | K6: Актуализир. сумма | L6: в т.ч. заемные
A7: 1 | C7: Балхашский район | D7: ТОО «Неокарбон» - реализован, с.Баканас,ул.Сейфуллина №122А | E7: Строительство наружных сетей газоснабжение производственной базы переработки рисовой шелухи в производство древесноугольных брикетов и углерод-кремнистого композита | F7: Реализован | G7: 50 | I7: 386.8 | K7: =I7 -> 386.8 | M7: 2025 г. | N7: 2025 г. | O7: 0.9936 | P7: Углерод-кремнистый композит 216 тонн | Q7: Проект действует. На сегодня задействованы 9 работников. После достижения мощности будет увеличено до 50 раб.мест. | R7: Усенов Досжан, 87075655767 | S7: Подведение недостающей ИКИ, ЦН ЗУ - Прочие земли.
A8: 2 | C8: Балхашский район | D8: ТОО "СЭМ и КО" | E8: Предприятие мясного животноводства. Приобретение биологических активов в виде племенного КРС, МРС | G8: 99 | H8: СКО | K8: 5000 | L8: 5000 | P8: МРС - 5018 КРС - 6189 | Q8: Скот закуплен, предприятие действует, проблемных вопросов нет | R8: Абуталипова Асель | S8: Кредитов АПК (СКО)
A9: 3 | C9: Енбекшиказахский район | D9: ТОО «Qazaq Global Food JV», Тескенсуский с/о | E9: Строительство завода по переработке фруктов и овощей (производству концентратов фруктовых соков, овощных и фруктовых пюре с инфраструктурой хранения сортировки и упаковки фруктов) | F9: Реализован | G9: 128 | I9: 10000 | K9: 10000 | L9: 7000 | M9: 2026 г. | N9: 2026 | O9: 30 | P9: Переработка до 70 -80 тысяч тонн фруктов и овощей в год | Q9: Строительство завершено, оборудование завезено и установлено. Акт ввода в эксплуатацию на стадии оформления. Текущее время проводится работа по поиску поставщиков сырья для переработки. Торжественное открытие завода запланировно на 19.06.2026 г. | R9: 87025552708 Жуматаев Ержан Ерболатович | S9: ЗУ на 5 лет. ЦН ЗУ - Пастбища.
A10: 4 | C10: Енбекшиказахский район | D10: ТОО FRESH FISH KZ | E10: Рыбоводство | F10: Реализуемые проекты, по линии кредитования АПК по опыту СКО | G10: 20 | H10: СКО | K10: 651.3 | L10: 500 | P10: 1512 тонн рыбы в год | Q10: Конкурсная комиссия одобрило финансирование по программе кредитование в сфере АПК (по опыту СКО) на приобретение оборудования для глубокой переработки форели и других видов рыб: свежей, мороженной, сушеной и копченой рыбы, а также красной икры. | R10: Мурат Аманжол, 87756327171
A11: 5 | C11: Енбекшиказахский район | D11: КХ «Айдарбаев» | E11: Расширение молочно товарной фермы | F11: Реализуемые проекты, по линии кредитования АПК по опыту СКО | H11: СКО | K11: 650 | L11: 650 | P11: 1270 голов, 6200 тонн в год | Q11: МТФ работает, проблемных вопросов нет | R11: Айдарбаев Ерик Серикович
A12: 6 | C12: Енбекшиказахский район | D12: ТОО «ABDI AGRO» | E12: Строительство молочно товарной фермы | F12: Реализуемые проекты, по линии кредитования АПК по опыту СКО | H12: СКО | K12: 1314.2 | L12: 1314.2 | P12: 400 голов, 2000 тонн в год | Q12: МТФ работает, проблемных вопросов нет | R12: Абдиев Ержан Шубаевич 87015558622
A13: 7 | C13: Енбекшиказахский район | D13: КХ «Алимжанов» | E13: Расширение молочно товарной фермы | F13: Реализуемые проекты, по линии кредитования АПК по опыту СКО | H13: СКО | K13: 199.5 | L13: 199.5 | P13: 831 голов, 3500 тонн в год | Q13: МТФ работает, проблемных вопросов нет | R13: Алимжанов Тілек
A14: 8 | C14: Енбекшиказахский район | D14: ТОО «Абди Агро» | E14: Строительство и эксплуатация систем влагосберегающих технологий | G14: 10 | I14: 601.8 | K14: 601.8 | R14: Абдиев Ержан Шубаевич
A15: 9 | C15: Жамбылский район | D15: ИП Сарсембаева Р.Г. | E15: Строительство и эксплуатация систем влагосберегающих технологий для выращивание кукурузы на зерно | F15: Инвестиционные проекты реализуемые по программе развития растениеводства. | H15: Растениевод | K15: 941 | P15: 2258 тонн в год | Q15: Приобретенное оборудование введено в эксплуатацию, проблемных вопросов нет | R15: Абулгазинов Марлен 87011112789
A16: 10 | C16: Илийский район | D16: АО "Каскеленское" | E16: Строительство и эксплуатация систем влагосберегающих технологий для выращивание кукурузы на зерно | F16: Инвестиционные проекты реализуемые по программе развития растениеводства. | G16: 20 | H16: Растениевод | K16: 386 | O16: 5882 | P16: 930 тонн в год | Q16: Приобретенное оборудование введено в эксплуатацию, проблемных вопросов нет
A17: 11 | C17: Илийский район | D17: ТОО Каргалы Крахмал | E17: Строительство и эксплуатация систем влагосберегающих технологий для выращивания кукурузы на зерно | F17: Инвестиционные проекты реализуемые по программе развития растениеводства. | G17: 10 | H17: Растениевод | K17: 142 | O17: 416 | P17: 343 тонн в год | Q17: Приобретенное оборудование введено в эксплуатацию, проблемных вопросов нет
A18: 12 | C18: Илийский район | D18: ТОО «Научно производственный центр Генофонд» | E18: Расширение молочно товарной фермы | F18: Реализуемые проекты, по линии кредитования АПК по опыту СКО | G18: 19 | H18: СКО | K18: 553.6 | L18: 553.6 | O18: 1162 | P18: 1800 голов, 7440 тонн в год | Q18: МТФ работает, проблемных вопросов нет | R18: Толемисов Махан
A19: 13 | C19: Илийский район | D19: ТОО «Ризык Агро» | E19: Расширение молочно товарной фермы | F19: Реализуемые проекты, по линии кредитования АПК по опыту СКО | G19: 23 | H19: СКО | K19: 1209.8 | L19: 1209.8 | O19: 5400 | P19: 629 голов, 3100 тонн в год | Q19: МТФ работает, проблемных вопросов нет | R19: Абулгазинов Марлен
A20: 14 | C20: Илийский район | D20: ТОО «Ак сут LLC» | E20: Расширение молочно товарной фермы | F20: Реализуемые проекты, по линии кредитования АПК по опыту СКО | G20: 50 | H20: СКО | K20: 300.7 | L20: 300.7 | O20: 184 | P20: 2592 голов, 6900 тонн в год | Q20: МТФ работает, проблемных вопросов нет | R20: Сембай Елжас
A21: 15 | C21: Талгарский район | D21: СПК «Племзавод «Алматы» - реализован, участок Малайсары. | E21: Развитие овцеводства породы Иль-Де-Франс в Жетысу | F21: Реализован | G21: 100 | I21: 750 | K21: 1500 | L21: 0 | M21: 2025 г. | O21: 2512 | P21: 1000 голов, 200 тонн мяса в год | Q21: Проект реализован. Ведутся селекционные работы: из г. Минск завезено 100 голов баранов-производителей породы Иль-де-Франс, сформировано маточное стадо численностью 1 500 голов. На площади 680 га проводятся работы по переводу земель в категорию орошаемых для внедрения влагосберегающих технологий. Получены технические условия на подключение к электрическим сетям, проектно-сметная документация прошла государственную экспертизу. В настоящее время осуществляется приобретение дождевальных (фрегатных) установок, монтаж которых запланирован на осень текущего года. | R21: Ахметжанов Рустем Кажиканович, 87775146500 | S21: ЗУ на 49 лет. ЦН ЗУ - 528 га-орошаемая пашня, 1 984 га- пастбище.
A22: 16 | C22: Талгарский район | D22: ТОО COFCO TRANS Бин 250640019716 | E22: Элеватор по производству кормовой муки | G22: 23 | H22: собственные средства | K22: 5500 | M22: 2026 г. | P22: 293 тыс тонн | Q22: На сегодняшний день строительно-монтажные работы выполнены на 75 %. Работы ведутся в соответствии с утвержденным графиком. Завершение проекта планируется в течение ближайших двух месяцев. В настоящее время на объекте продолжаются основные строительные и организационные мероприятия, направленные на своевременное завершение всех предусмотренных этапов работ. С учетом текущих темпов реализации проекта, полный ввод объекта в эксплуатацию ожидается до начала уборочной кампании урожая.
A23: 17 | C23: Талгарский район | D23: ТОО «Байсерке Агро» | E23: Расширение молочно товарной фермы | F23: Реализуемые проекты, по линии кредитования АПК по опыту СКО | H23: СКО | K23: 500 | L23: 500 | P23: 1125 голов, 4650 тонн в год | Q23: МТФ работает, проблемных вопросов нет | R23: Жунисбеков Галыжан
A24: 18 | C24: Уйгурский район | D24: ТОО "Eco Park Tour" | E24: Строительство и эксплуатация систем влагосберегающих технологий длч сада по выращиванию яблок и абрикоса | F24: Инвестиционные проекты реализуемые по программе развития растениеводства. | G24: 10 | H24: Растениевод | J24: 217 | K24: 217 | N24: 2017 декабрь | O24: 1,01 га | P24: 537 тонн в год | Q24: Реализованный проект | R24: Абдулминов Бахтияр Баратович | S24: 1,01 га
A25: 19 | C25: Уйгурский район | D25: ТОО Kolzhat Agro | E25: Строительство и эксплуатация систем влагосберегающих технологий для выращивания люцерны | F25: Инвестиционные проекты реализуемые по программе развития растениеводства. | H25: Растениевод | K25: 527.237 | O25: 1490 | P25: 1249 тонн люцерны с 1490 га | Q25: Приобретенное оборудование введено в эксплуатацию, проблемных вопросов нет | R25: Нимилостев Петр Петрович
A26: 20 | C26: Уйгурский район | D26: ТОО «Асем калжат» | G26: 180 | I26: 7500 | K26: 7500
A27: 21 | C27: г.Конаев | D27: ТОО «Оспанова Девелопмент» - реализован. | E27: Строительство рыбопромышленного комплекса | F27: Реализован | G27: 500 | I27: 9800 | K27: 9800 | L27: 300 | M27: 2023 г. | O27: 27 | P27: 1 тыс. тонн рыбы в год | Q27: Первый этап проекта реализован и введен в эксплуатацию в октябре 2023 года. В настоящее время осуществляется выращивание форели и беррамунди (морского окуня). От реализации последующих этапов проекта, предусматривавших выращивание карпа, инвестор отказался в связи с экономической нерентабельностью. Согласно Правилам субсидирования инвестиционных вложений, сумма возмещения затрат по первому этапу составила 90 млн тенге, что соответствует лишь 0,85 % от стоимости первого этапа проекта. | R27: Бектемисов Максим Сакенович | S27: Подведение недостающей инфраструктуры ЦН ЗУ - прочие земли
A28: 22 | C28: г.Конаев | D28: ТОО «Қапшагай бидай өнімдері» | G28: 350 | I28: 12000 | K28: 12000
A29: 23 | C29: г.Алатау | D29: ТОО «ФрутАрт» | G29: 247 | I29: 42800 | K29: 42800
A30: 24 | C30: Райымбекский район | D30: ТОО "Сарыбастау - ББ" | E30: Строительство и эксплуатация систем влагосберегающих технологий для выращивания картофеля | F30: Инвестиционные проекты реализуемые по программе развития растениеводства. | G30: 10 | H30: Растениевод | K30: 407 | O30: 200 | P30: 1500 тонн картофеля | Q30: В текущем году освоено 169 га из запланированных 200 га. На площади 50 га произведён посев картофеля, на 110 га — ячменя. РКС не проходили. | S30: нет
A31: 25 | C31: Кегенский район | D31: СПК «Талас» | E31: Расширение молочно-товарной фермы | F31: Реализуемые проекты, по линии кредитования АПК по опыту СКО | G31: 50 | H31: СКО | I31: 492 | K31: 492 | L31: 492 | M31: 2025 г. | O31: 745 | P31: 422 голов, 1375 тонн в год | Q31: Ведутся СМР по расширению. МТФ работает, проблемных вопросов нет | R31: Жамбаев Жусип Ахметказиевич 87010813468. | S31: З/У
A32: 26 | C32: Кегенский район | D32: ТОО «KeгeнMяcПpoм» | E32: Мясокомбинат с предубойным откормочным комплексом | F32: Реализован | G32: 50 | I32: 2700 | K32: 2700 | M32: 2025 г. | N32: 2025 г. | O32: 380 | P32: 10 тонн мяса в сутки | Q32: Все оборудование на площадке для убоя скота прошло полную проверку. На объект строительства выдан технический паспорт (техпаспорт). | R32: Баймолдаев Токтар Аскарович +7 701 311 1151 | S32: З/У
A33: 27 | C33: Кегенский район | D33: Производство тонкой шерсти ТОО «MERGEN HOLDING» | E33: Строительство производственной базы по переработке шерсти «MERGEN HOLDING» | G33: 200 | H33: собственные средства | K33: 1500 | M33: 12.2026 г. | P33: 2 тыс тонн | Q33: Наличие земельного участка; наличие ПСД (АПЗ, рабочий проект, эскизный проект, заключение); Активно ведутся СМР, выполняется комплекс земляных работ, включая разработку и подготовку грунта. Параллельно осуществляются бетонные работы по устройству основных конструктивных элементов. Ведётся монтаж металлоконструкций в соответствии с утверждённой ПСД
A34: 28 | C34: Карасайский район | D34: ИП «Baitelov» | E34: Расширение садкового рыбоводного хозяйства по выращиванию ценных видов рыб с объемом 120 тонн в год | G34: 6 | H34: собственные средства | I34: 120 | K34: 120 | M34: 2025 | P34: 120 тонн форели в год | Q34: Рыбоводное хозяйство расположен на земельном участке площадью 33,5 га. Для выращивания молоди рыбы имеются 5 естественных прудов общей площадью 2326,4 м кв., которые предназначены для выращивания мальков форели до товарной массы. Пруды оборудованы садками общей площадью 7861 м3 оснащены магистральными каналами водоподачи и дренажной системой. Водоснабжение производится из артезианской скважины с температурным режимом 13-16°С. Рыбоводное хозяйство оснащен необходимой инфраструктурой и оборудованием включая склад для хранения кормов площадью 0,5 м2. Малька форели карпа закупают от местных производителей.
A35: 29 | C35: Кегенский район | D35: Командитное товарищество «Great Steppe Heritage» | E35: Расширение и автоматизация садковой линии | G35: 28 | H35: собств. ср-ва 400 млн, заемные 1,650 млрд. | I35: 2050 | K35: 2050 | M35: 2025 | P35: 500 тонн форели в год | Q35: Договор с ТОО «Мойнакская ГЭС» на 10 лет по аренде водной глади для установки садков подписан. Установлены 12 садков диаметром 22 м. Провел работу по зарыблению в количестве 250 тыс. штук мальками форели средней массой 12 гр. Корма используются импортные – ALLER AQUA. Кроме того, 2025 году планируется расширение и автоматизация садковой линии. | R35: Байзаков Нурлан диретор 87017557507 Байкен Бекетаевич 87028216346
A36: 30 | C36: Енбекшиказахский район | D36: ТОО «TogizBulaq» | E36: Создание прудового рыбоводного хозяйства по выращиванию ценных видов рыб с объемом 360 тонн в год | G36: 21 | H36: собственные средства | I36: 200 | K36: 200 | M36: 2025 | P36: 360 тонн форели в год | Q36: В мае 2022 года начато строительство рыбоводного комплекса на земельном участке площадью 75 гектаров. Проектно-сметная документация прошла государственную экспертизу. Проведена работа по установке оборудования (бассейны, инкубационные аппараты). Запуск 1 этапа выращивание форели начато в начале 2024 года. Проделано 50% работы.
A37: 31 | C37: Енбекшиказахский район | D37: ТОО "АгроАкваКомплекс" | E37: Расширение прудового рыбоводного хозяйства по выращиванию ценных видов рыб с объемом 279 тонн в год | G37: 14 | H37: заемные средства | I37: 300 | K37: 300 | M37: 2025 | P37: 279 тонн карп.форели | Q37: имеется 7 прудов, планируется увеличить до 20
A38: 32 | C38: Жамбылский район | D38: ТОО " ТехноСнаб 2002" | E38: Создание УЗВ Рыбопромышленный комплекс по выращиванию форели и осетра | G38: 13 | H38: собственные средства | I38: 450 | K38: 450 | M38: 2025 | P38: 150-200 форель и осетра | Q38: Ввод в эксплуатацию в августе 2025 г.
A39: 33 | C39: Илийский район | D39: ТОО "Кайнар Балык" | E39: Инкуб.цех, 15 садков | H39: собственные средства | M39: 2026

Sheet Реализуемые
D2: кол | E2: сумма | F2: Раб. места
C3: Реализуемые | D3: 28 | E3: 404318.03 | F3: 8284
A7: № | B7: № | C7: Район | D7: Наименование компании | E7: Наименование проекта | F7: Стадия проекта | G7: Раб. Места | H7: Финансирование | I7: Стоимость, млн. тенге | M7: Ввод объекта по РКС | N7: Ввод объекта по факту | O7: Площадь земельного участка, га | P7: Мощность проекта и производительность | Q7: Текущий статус | R7: ФИО руководителя, контакты | S7: Меры господдержки
H8: Собственные, АКК/БРК, Растениевод, СКО | I8: Всего по РКС | J8: Вне РКС | K8: Актуализир. сумма | L8: в т.ч. заемные
A9: 1 | C9: Балхашский район | D9: ТОО «Баканас рис», Берекенский с/о | E9: Выращивание риса в Алматинской области | F9: Реализуемые проекты, прошедшие РКС | G9: 35 | I9: 600 | K9: 600 | M9: 2027 г. | N9: 2027 г. | O9: 707.6 | P9: от 5 000-7 000 тонн в год | Q9: В рамках реализации проекта выполняются работы по ограждению территории и проведению земляных работ. Приобретена сельскохозяйственная техника, обеспечено водоснабжение участка. В целях апробации технологии произведен посев риса на пробном участке площадью 50 га. Основной объем посевных работ запланирован на следующий год после получения финансирования от инвестора. В текущем году объем инвестиционных вложений составил 78,5 млн тенге. Реализация проекта осуществляется в соответствии с бизнес-планом. | R9: Рахманов Шавкат Бахтибаевич 87778880877, 87006804511 Орал | S9: ЗУ на 5 лет. ЦН ЗУ - Пашня орошаемая.
A10: 2 | C10: Балхашский район | D10: ТОО «Баканас Байтак Агро» | E10: Строительство комплекса по переработке люцерны, кукурузы и других кормовых сельскохозяйственных культур | F10: Реализуемые проекты, прошедшие РКС в 2026 | G10: 13 | I10: 869.1 | K10: 869.1 | M10: 2027 | O10: 13 | Q10: Получен государственный акт, однако в связи с некорректно указанным целевым назначением земельного участка документ сдан на корректировку. Начаты земельные работы. | S10: нет
A11: 3 | C11: Енбекшиказахский район | D11: ТОО «Kazakhstan Central Asia Industrial Company., Ltd», Балтабайский с/о | E11: Переработка биологических отходов и производство органических, экологически чистых удобрений животного происхождения | F11: Реализуемые проекты, прошедшие РКС | G11: 30 | I11: 7200 | K11: 7200 | M11: 2026 | N11: 2026 | O11: 10 | P11: Мясокостная мука – 15 000 тонн, технический жир – 5 000 тонн | Q11: Оборудование из КНР доставлено. В настоящее время проводятся работы по его монтажу и установке. Для выполнения пусконаладочных работ ожидается поставка необходимых кабелей и проводов. Получение акта ввода объекта в эксплуатацию планируется в июле 2026 года. Реализация проекта осуществляется в соответствии с бизнес-планом. | R11: Руководитель - Sun Jinggang, 87762611499 Дуйсен
A12: 4 | C12: Енбекшиказахский район | D12: ТОО «Дусан Инжиниринг», Акшиский с/о | E12: Организация МТФ на 1 200 голов КРС | F12: Реализуемые проекты, прошедшие РКС | G12: 50 | I12: 31840 | K12: 31840 | L12: 2400 | M12: 2034 г. | O12: 84 | P12: до 27 тыс. тонн в год | Q12: Приобретен земельный участок площадью 576 га, пробурена скважина. Закуплены две дождевальные установки производства КНР, достигнута договоренность о поставке еще трех установок. Получено АПЗ на систему орошения, ведется работа по оформлению лицензии на недропользование. По проекту МТФ разработана ПСД, получено положительное заключение государственной экспертизы. Приобретены четыре трактора с навесным оборудованием и прицепами, выполнены агротехнические работы, создано 9 рабочих мест. В текущем году планируется перевод 250 га земель на орошаемое земледелие с применением влагосберегающих технологий. Финансирование проекта планируется через АО «АКК». В связи с отсутствием финансирования строительство МТФ перенесено на 2027 год. Проект реализуется поэтапно: создание кормовой базы, строительство МТФ с приобретением маточного поголовья КРС, а также строительство перерабатывающих цехов и расширение поголовья. Объем инвестиций в проект в 2025 году составил 1,2 млрд тенге. Дополнительно в текущем году инвестировано 200 млн тенге. Реализация проекта осуществляется в соответствии с бизнес-планом. | R12: 8 775 224 7474 ЫСҚАҚ ТАЛҒАТ БАТЫРҰЛЫ | S12: ЗУ на 5 лет. ЦН ЗУ - Пастбища.
A13: 5 | C13: Енбекшиказахский район | D13: ТОО «QazEcoDan», Масакский с/о | E13: Строительство Элеватора -комплекса по приемке, очистке, сушке и хранению зерновых и масленичных культур, производству комбинированных кормов | F13: Реализуемые проекты, прошедшие РКС | G13: 51 | I13: 7975.333 | K13: 7975.333 | M13: 1 этап - 2026 г. 2 этап - 2027 г. | N13: 1 этап - 2026 г. 2 этап - 2027 г. | O13: 9.6 | P13: Очистка, сушка: 40-60 тонн/час Хранение в силосах: 30 тыс. тонн Мощностью производства кормов 120 тонн/сутки | Q13: Строительство I очереди проекта завершено на 98%, акт ввода объекта в эксплуатацию находится на согласовании. Объем инвестиций составил 5,8 млрд тенге. Завершено строительство основных производственных объектов, включая сушильную печь, силосы, ЛЭП-35, газгольдер, железнодорожный тупик и монтаж технологического оборудования. На завершающей стадии находятся работы по объектам вспомогательной инфраструктуры. Для повышения эффективности проекта требуется подключение к природному газу, что позволит снизить себестоимость сушки зерновых культур. Также рассматривается расширение железнодорожного тупика путем строительства трех дополнительных веток. Вопрос строительства газопровода от п. Казтай Ултараков прорабатывается с местными исполнительными органами. | R13: 87716111117 Ерлан руководитель проекта, Руководитель Кайралапин Казбек +7 701 227 0091 | S13: ЗУ на 10 лет. ЦН ЗУ - Пастбища.
A14: 6 | C14: Енбекшиказахский район | D14: ТОО «Мың жылқы шаруа қожалығы», Масакский с/о Саймасай, Каратурык. | E14: Строительство и организация деятельности конефермы | F14: Реализуемые проекты, прошедшие РКС | G14: 20 | I14: 1576.6 | K14: 1576.6 | M14: 2027 г. | O14: 4457.7 | P14: 1 000 лошадей | Q14: Введутся работы по подготовке к СМР, произведен закуп лошадей в кол-ве 360 голов на 432 млн тенге. На 5 га планируется строительство кошары, навесов, загонов, остальную землю использовать под пастбище. | R14: Руководитель - Оразалин Галымжан Серикович 87011116911 | S14: ЗУ на 5 лет. ЦН ЗУ - Пастбища.
A15: 7 | C15: Енбекшиказахский район | D15: ТОО «K&J AGRO» | E15: Строительство теплицы по выращиванию шампиньонов | F15: Реализуемые проекты, прошедшие РКС в 2026 | G15: 100 | I15: 1500 | K15: 1500 | M15: 2029 | O15: 4 | P15: 2 тыс. тонн в год | Q15: Планируется заказ проектно-сметной документации. Ожидает подведения инфраструктуры на ИЗ «Шелек» | R15: Ракыш Темирлан | S15: нет
A16: 8 | C16: Жамбылский район | D16: ТОО «Кок Тениз К», Темиржолский с/о | E16: Расширение мощностей по переработке кукурузы с 10 000 до 50 000 тонн в год | F16: Реализуемые проекты, прошедшие РКС | G16: 20 | H16: СКО | I16: 750 | K16: 1500 | M16: 2029 г. | O16: 3080 | P16: 50 тыс тонн в год | Q16: 15.06.2026 г. планируется доставка трех дождевальных установок для орошения земельных участков общей площадью 200 га. Проводится работа по выбору поставщика дождевальных установок для организации орошения 1 000 га земель, предназначенных под многолетние культуры. Объем инвестиций в проект в текущем году составляет 750 млн тенге. Реализация проекта осуществляется в соответствии с утвержденным бизнес-планом. | R16: Кошкинов Ержан Абдулинович +77015396668, 8 706 407 9137 Ерасыл - сын | S16: ЗУ на 10 лет. ЦН ЗУ - пашня богарная
A17: 9 | C17: Жамбылский район | D17: ТОО «НПЦ Генофонд» | E17: Строительство МТФ на 600 голов КРС | F17: Реализуемые проекты, по линии кредитования АПК по опыту СКО | G17: 18 | H17: СКО | K17: 2400 | L17: 1400 | P17: 600 голов, 5000 тон в год | Q17: Завршение строительствв МТФ планируется в до конца июля месяца текущего года, для приобретения оборудования МТФ, доильного зала, КРС, Конкурсной комиссией утверждено финансирование на 1,4 млрд тенге. Финансирование планируется в текущем месяце. | R17: 8-701 303 5050 Толемисов Махан Кенжегазинович, бухгалтер - 8-701 303 22 88 Кумис Мурзалинова | S17: ПСД на стадии разработки, представлен государственный акт на земельный участок
A18: 10 | C18: Жамбылский район | D18: ТОО «Алматы құс фабрикасы Жетісу» | E18: Разведение птицы на мясо, племенной птицы и молодняка | G18: 6000 | H18: БРК и собственные средства | K18: 146300 | M18: 2028 г. | P18: 100 тыс тонн | Q18: ТОО «Алматы құс фабрикасы Жетісу», стс-сть 146,3 млрд тенге. Площадь - 5838,4 га. Проблемные вопросы: подведение инфраструктуры. Текущее состояние: ГЭ имеется, ожидается ПСД по инфраструктуре. ПСД по автодорогам и мостам подготовлена. Получено АПЗ и согласован эскизный проект.
A19: 11 | C19: Илийский район | D19: ТОО «Компания «Сары Булак», Аксайский с/о, село Аксай уч.1531 | E19: По переработке куриного помёта в органические удобрения | F19: Реализуемые проекты, прошедшие РКС | G19: 60 | I19: 550 | K19: 550 | M19: 2026 г. | N19: 2027 г. | O19: 6 | P19: Переработка куриного помёта – 200 тонн в сутки | Q19: Лагуны для хранения и переработки птичьего помета выполнены и забетонированы. Вопрос получения технических условий от АЖК остается нерешенным. Проведена повторная встреча с руководством АЖК, достигнута договоренность о повторной подаче документов на получение ТУ. Оборудование закуплено и находится на складах без монтажа и ввода в эксплуатацию. Получение акта ввода объекта в эксплуатацию планируется в 2027 году. | R19: 87012281400 Берик Меирханович | S19: ЦН ЗУ - пастбище
A20: 12 | C20: Илийский район | D20: ТОО «Alfalfa», Аксайский с/о | E20: Выращивание люцерны | F20: Реализуемые проекты, прошедшие РКС | G20: 30 | H20: СКО | I20: 5000 | K20: 5000 | L20: 1500 | M20: 2026 г. | O20: 1700 | P20: Тюкованная люцерна 12 000 тонн/год, гранулированная люцерна 8 000 тонн в год | Q20: Получено финансирование от АО «СПК Конаев» в размере 1,5 млрд тенге. На стадии завершения строительно-монтажные работы по внутренним сетям водоснабжения. Поставлены 8 дождевальных установок, не введены в эксплуатацию, 3 установки находятся в пути. В текущем году будут установленны 11 дождевальных машин покрывающих 700 га земли, в 2027 году планируется приобретение и установка дождевальных машин покрывающих оставшиеся 1000 га. Осуществляется поиск инвестора/инвестиций для строительства наружных сетей водоснабжения, проводится расчет окупаемости проекта. | R20: Руководитель - Яний Сергей Владимирович, Ауельбек 87017444703 | S20: Подведение недостающей ИКИ, ЦН ЗУ - пастбище
A21: 13 | C21: Илийский район | D21: ТОО «LUX Grand Park» | E21: Строительство молочно-товарной фермы в Илийском районе Алматинской области | F21: Реализуемые проекты, прошедшие РКС в 2026 | G21: 100 | I21: 650 | K21: 650 | M21: 2027 | O21: 282 | P21: 876 000 литров натурального молока в год | Q21: Получили выписку РКС | S21: нет
A22: 14 | C22: Илийский район | D22: ТОО «Агрофирма Dinara-Ranch» | E22: Растениеводство на орошаемых землях для создание кормовой базы КРС | F22: Реализуемые проекты, прошедшие РКС в 2026 | G22: 18 | I22: 700 | K22: 700 | M22: 2028 | O22: 390.2 | P22: 6 248 т. кормов в год | Q22: Начаты посевные работы
A23: 15 | C23: Илийский район | D23: АО «АЛЕЛЬ АГРО» | E23: Строительство завода по переработке отходов птицеводства (производство кормовых добавок из пера, кишок, крови, падежа) | F23: Реализуемые проекты, прошедшие РКС в 2026 | G23: 27 | I23: 670 | K23: 670 | M23: 2027 | O23: 3.2 | P23: 1.Линия переработки крови (4.5 т/день)2.Линия переработки кишок (9т/день)3. Линия переработки пера (9т/день) | Q23: Получили выписку от РКС | S23: нет
A24: 16 | C24: Карасайский район | D24: ТОО «Жигалма» (Caspian Beverage Holdings), Жамбылский с/о | E24: Производство безалкогольных напитков и минеральных вод | G24: 250 | I24: 15800 | K24: 15800 | L24: 5000 | M24: 2026 г. | N24: 2027 г. | O24: 10 | P24: 500 млн. литров продукции в год, 120 млн. единиц упаковки в год | Q24: Заявление на получение архитектурно-планировочного задания (АПЗ) направлено. Подана заявка в АЖК на ТУ -2 МВ (врменная). 24.04.2026 года получено официальное письмо от АЖК, согласно которому запланированы работы по увеличению мощности на подстанции «Чемолган», к которой будет осуществлено подключение объекта компании. Осуществляется поиск инвестора/инвестиций. | R24: Руководитель - Ахметов Алмат Сагындык улы, 87777799078, Рустам Давлетов +7 (777) 779 90 78 | S24: ЗУ на 3 года. ЦН ЗУ - пашня орошаемая
A25: 17 | C25: Талгарский район | D25: ТОО "ALATAU GREEN PRODUCTION" | E25: Строительство мультикультурного тепличного комплекса на 8 гектар | G25: 400 | H25: БРК | J25: 17300 | L25: 13408.8 | M25: 2025-2028 г. | O25: 8 | P25: 4 тыс тонн | Q25: Общая стоимость проекта составляет 17,3 млрд тенге. Финансирование осуществляется за счет собственных средств компании и кредита АО «Банк Развития Казахстана». Получены АПЗ и технические условия на подключение к инженерным сетям. Разрешение на строительство мостового перехода через Большой Алматинский канал получено. Проектно-сметная документация находится на завершающей стадии. Проект предусматривает создание 400 постоянных рабочих мест. Ввод объекта в эксплуатацию планируется до конца III квартала 2026 года, выход на полную проектную мощность — в 2027 году.
A26: 18 | C26: Уйгурский район | D26: ТОО «Rancho Hampshire», Малодиханский с/о | E26: Организация производственной базы сельхозназначения (Разведение английской породы овец Гемпшир и выращивание кукурузы, люцерны и разнотравья) | F26: Реализуемые проекты, прошедшие РКС | G26: 50 | I26: 1000 | K26: 1000 | M26: 1 этап 2026 г. 2 этап 2028 г. | N26: 1 этап 2026 г. 2 этап 2028 г. | O26: 1500 | P26: Проектная мощность на 2000 голов, факт более 400 голов | Q26: Текущее сосотояние: Проект находится на стадии реализации. Степень готовности – 50 %. Проблемные вопросы: ТОО зарегистрировано в Илийском районе. | R26: Директор - Чепис Сергей +7 701 555 22 28 | S26: ЗУ на 10 лет. ЦН ЗУ - пастбище.
A27: 19 | C27: Уйгурский район | D27: ТОО «Харвест Агро Холдинг» | E27: Создание агро-индустриального кластера «Harvest» в Уйгурском районе | F27: Реализуемые проекты, прошедшие РКС | G27: 60 | I27: 18200 | K27: 18200 | M27: 2029 г. | O27: 100 | P27: до 50 тыс. тонн кукурузы и 15 тыс. тонн сои в год | Q27: 30.01.2026 года состоялось заседание земельной комиссии, по итогам которого одобрено предоставление ЗУ площадью 3 000 га сроком на 10 лет из запрошенных 10 000 га на 49 лет. 27.03.2026 года проведены общественные слушания, где было одобрено выдача еще 2 000 га.
A28: 20 | C28: Уйгурский район | D28: ТОО «Harvesto Logistics» | E28: Строительство завода по производству семян гибридов кукурузы и подработке, хранению товарного зерна | F28: Реализуемые проекты, прошедшие РКС в 2026 | G28: 70 | I28: 3600 | K28: 3600 | M28: 2028 г. | O28: 100 | P28: до 108 тыс. тонн хранения с суточной переработкой до 1 200 тонн в сезон. | Q28: На стадии прохождения земельной комиссии | R28: Мурат Амангельдиевич | S28: нет
A29: 21 | C29: Уйгурский район | D29: ТОО «Kaz Corn» | E29: Освоение залежных земель для возделывания гибридов кукурузы и родительских форм путем внедрения водосберегающих технологий | F29: Реализуемые проекты, прошедшие РКС в 2026 | G29: 35 | I29: 8500 | K29: 8500 | M29: 2027 г | O29: 5000 | P29: 4 000 га товарной кукурузы, 1 000 га семеноводство | Q29: На стадии прохождения земельной комиссии | R29: Мурат Амангельдиевич | S29: нет
A30: 22 | C30: Уйгурский район | D30: Прима-Кус | E30: Строительство птицеводческого комплекса замкнутого цикла по производству и переработке мяса бройлера | G30: 140 | I30: 24477 | K30: 24477 | M30: 2028 г. | O30: 542 | Q30: ТОО «Прима Құс» — птицефабрика,строительство 3-й этап. Общая потребность в инвестициях составляет 13 500,0 млн тенге, финансирование проекта обеспечено в полном объеме. На текущий момент строительно-монтажные работы выполнены на 97,1%. Ввод объекта в эксплуатацию запланирован на декабрь 2026 года. После выхода на проектную мощность объем производства будет увеличен до 36 000 тонн мяса птицы в живом весе в год.
A31: 23 | C31: г.Конаев | D31: ТОО «Asian International Trading Company», Шенгельдинский с/о, участок Кербулак | E31: Строительство завода по производству комбикорма из плющенной кукурузы | F31: Реализуемые проекты, прошедшие РКС | G31: 158 | I31: 2110 | K31: 2110 | M31: 2029 г. | O31: 20 | P31: 150,0 тыс тонн в год | Q31: Работы по проекту в настоящее время не ведутся. Проект реализуется на территории, прилегающей к СЭЗ «Конаев». Руководитель компании находится в КНР и планирует прибыть в конце июня – начале июля текущего года. В связи с неактивностью инвестора предлагается вынести на заседание РКС по отзыву ЗУ. | R31: Лань Сяо Янь, 87055302473, Кристина 8 (706) 410 10 98 | S31: ЗУ на 1 год. ЦН ЗУ - прочие земли
A32: 24 | C32: г.Конаев | D32: ТОО «Smart Adam Agro» | E32: Выращивание прочих многолетних культур | G32: 19 | I32: 1200 | K32: 1200 | O32: 900 | P32: Выращивание и производство кормов 5 тыс. тонн / год | R32: Ибекеев Ержан Сембекулы
A33: 25 | C33: г.Конаев | D33: TOO «Arbo Volt» | E33: Строительство питомника с производственной базы | F33: Реализуемые проекты, прошедшие РКС | G33: 100 | I33: 2400 | K33: 2400 | M33: 2028 | O33: 109 | P33: 16 000 саженцев Paulownia Tomentosa | Q33: Получен гос акт. Начали разработку плана детальной планировки. Разработку ПДП планируется завершить в августе 2026 года. . | S33: нет
A34: 26 | C34: г.Алатау | D34: ТОО «Молочная Долина», | E34: Строительство МТФ на 1200 голов | F34: Реализуемые проекты, прошедшие РКС | G34: 100 | I34: 18700 | K34: 18700 | L34: 15000 | M34: 2028 г. | O34: 1300 | P34: 13,5 тыс. тонн в год | Q34: Проект готовится к направлению на ГЭ. На поливных ЗУ посеяно 250 га люцерны, кукурузы на корма. Вопрос частичного финансирования рассматривается АО "СПК Конаев". 03.06.2026г. при рассмотрении проект на Комиссии проект был направлен на доработку, так как отсутствовало ПСД и другие документы, разрезающие строительство МТФ на территории города Алатау. | R34: Разумовский Дмитрий Михайлович +7 705 677 9447 dmitriy.r.kz@icloud.com | S34: ЗУ на 49 лет. ЦН ЗУ - пастбище.
A35: 27 | C35: г.Алатау | D35: ТОО «ПепсиКо ЦА» | E35: Завод по производству соленых закусок | F35: Реализуемые проекты, прошедшие РКС | G35: 300 | I35: 81000 | K35: 81000 | L35: 71000 | M35: 2026 г. | N35: 2026 г. | O35: 26.47 | P35: 21 тыс. тонн продукта (чипсы Lay's) | Q35: Ведутся СМР | R35: Маргулан +7 701 722 2727 | S35: ЗУ на 4 года 11 мес. ЦН ЗУ - 15,0га- пашня орошаемая, 11,5 га - пастбища
A36: 28 | C36: Райымбекский район | D36: ТОО «QARASAZ MILK» | E36: Производственное предприятие по переработке шкур | F36: Реализуемые проекты, прошедшие РКС в 2026 | G36: 30 | I36: 700 | K36: 700 | M36: 2027 г. | O36: 13 | P36: Переработка шкур КРС и МРС – порядка 10 000 штук в год. | Q36: На стадии оформления земельного участка | R36: Алиева Дамира Нурболовна +7 777 777 1788 | S36: З/У

Sheet Расширение
D2: кол | E2: сумма | F2: Раб. места
C3: Расширение | D3: 2 | E3: 3972.2 | F3: 60
A6: № | B6: № | C6: Район | D6: Наименование компании | E6: Наименование проекта | F6: Стадия проекта | G6: Раб. Места | H6: Финансирование | I6: Стоимость, млн. тенге | M6: Ввод объекта по РКС | N6: Ввод объекта по факту | O6: Площадь земельного участка, га | P6: Мощность проекта и производительность | Q6: Текущий статус | R6: ФИО руководителя, контакты | S6: Меры господдержки
H7: Собственные, АКК/БРК, Растениевод, СКО | I7: Всего по РКС | J7: Вне РКС | K7: Актуализир. сумма | L7: в т.ч. заемные
A8: 1 | C8: Жамбылский район | D8: ТОО «Happy Farm» | E8: Строительство молочно товарной фермы | F8: Реализуемые проекты, по линии кредитования АПК по опыту СКО | H8: СКО | K8: 1472.2 | L8: 1472.2 | P8: 408 голов, 2000 тонн в год | Q8: СМР не завершен, срок завершения строительства планируется на 10.2026 года, скот и оборудование завезено в полном объеме, монтаж доильного зала завершен, начаты пусконаладачные работы. | R8: Маметов Марат
A9: 2 | C9: Карасайский район | D9: АО "АзияАгроФуд" | E9: Глубокая переработка по переработке сельскохозяйственной продукции. Приобретение оборудования. | G9: 60 | H9: СКО | K9: 2500 | L9: 2500 | P9: 110 тыс тонн в год | Q9: Произведена предоплата за изготовление оборудования в размере 60% от суммы контрактов. Срок поставки оборудования по контракту август 2026 года. Начало монтажа приобретенного оборудования запланирована на сентябрь 2026 года. | R9: Ашенов Саян | S9: Кредитов АПК (СКО)

Sheet Проблемные
D2: кол | E2: сумма | F2: Раб. места
C3: Проблемные | D3: 14 | E3: 190415 | F3: 1079
A6: № | B6: № | C6: Район | D6: Наименование компании | E6: Наименование проекта | F6: Стадия проекта | G6: Раб. Места | H6: Финансирование | I6: Стоимость, млн. тенге | M6: Ввод объекта по РКС | N6: Ввод объекта по факту | O6: Площадь земельного участка, га | P6: Мощность проекта и производительность | Q6: Текущий статус | R6: ФИО руководителя, контакты | S6: Меры господдержки
H7: Собственные, АКК/БРК, Растениевод, СКО | I7: Всего по РКС | J7: Вне РКС | K7: Актуализир. сумма | L7: в т.ч. заемные
A8: 1 | C8: Балхашский район | D8: ТОО «Тайда животноводство», Бакбактинский с/о | E8: Строительство агропромышленного комплекса по производству яиц | F8: Проблемный | G8: 68 | I8: 3120 | K8: 3120 | M8: 2027 г. | N8: 2027 г. | O8: 50 | P8: 100 млн. яиц в год | Q8: ПСД на государственной экспертизе с 28.04,2026 года, еще не получено, так как срок рассмотрения 1,5 месяца. Ориентировочный выход с ГЭ 20.06.2026г. В связи с неактивностью инвестора предлагается вынести на заседание РКС по отзыву ЗУ. | R8: Руководитель - Ян Цинхай, Уаджитова Амина Абдримовна, 87076408018 | S8: ЗУ на 5 лет. ЦН ЗУ - Прочие земли.
A9: 2 | C9: Енбекшиказахский район | D9: ТОО «AGROFINANCE», ИЗ «Шелек» | E9: Строительство ультрасовременного фруктохранилища в Алматинской области | F9: Проблемный | G9: 40 | I9: 10500 | K9: 10500 | M9: 2028 г. | O9: 5 | P9: 10 000 тонн | Q9: Проект планируется к реализации на территории ИЗ «Шелек». Начало работ по подведению ИКИ ожидается через 2 месяца, завершение — в 2027 году. Проведены переговоры с инвестором. В настоящее время инвестор находится за границей. Представитель инвестора 30.06.2026 г. связался с работниками УКИЗ договорились о выезде 07.07.2026 г. чтоб рассмотреть предложения по новым ЗУ. Но сегодня так и не приехал, сославшись что выехал за границу, как будет в Алматы выйдет на связь. В связи с неактивностью инвестора предлагается вынести на заседание РКС по отзыву ЗУ. . | R9: 87781075132 Пасков Иван Степанович | S9: Размещение ИЗ «Шелек». ЦН ЗУ - Пастбища.
A10: 3 | C10: Енбекшиказахский район | D10: TOО «Тепличный агропромышленный комплекс Синтай», Каражотинский с/о | E10: Выращивание в тепличном комплексе томаты, огурцы, перец, листья салатов, с последующей упаковкой для реализации. Комплекс будет состоять из 46 теплиц площадью каждой по 1 га, цех по упаковке, складские помещения, техничесие помещения. | F10: Проблемный | G10: 100 | I10: 3250 | K10: 3250 | M10: 2027 г. | O10: 50 | P10: 1 066 тыс тонн в год | Q10: На СВХ осуществляется таможенное оформление поставленного оборудования (6 экскаваторов) и металлических каркасов для теплиц. Подготовлены документы на изменение целевого назначения земельного участка под промышленное использование. После завершения процедуры планируется его выкуп. Реализация проекта затягивается в связи с разногласиями между инвестором и руководителем ТОО, препятствующими проведению проектных работ. В связи с неактивностью инвестора предлагается вынести на заседание РКС по отзыву ЗУ. | R10: Руководитель - Ибраев Куандык Аулиханович, инвестор - Ян Цинхай, Уаджитова Амина Абдримовна, 87076408018 | S10: ЗУ на 5 лет. ЦН ЗУ - Пастбища.
A11: 4 | C11: Енбекшиказахский район | D11: ТОО «Батал Агро», Аватский с/о | E11: Производство семян кукурузы родительских форм | F11: Проблемный | G11: 85 | I11: 3500 | K11: 3500 | L11: 1500 | M11: 2027 г. | O11: 94 | P11: До 559 тонн семян | Q11: На полученном земельном участке площадью 94 га были проведены подготовительные работы к посевной кампании. Однако посевная не была осуществлена в связи с выявлением факта двойного правообладания на данный участок. По состоянию на настоящее время материалы обращения находятся на рассмотрении в Управлении полиции Енбекшиказахского района. По результатам рассмотрения в пределах компетенции органом полиции будет принято соответствующее процессуальное решение в порядке и сроки, установленные законодательством Республики Казахстан. | R11: 87773277919 Айдарбаев Берик Ерикович 8 705 265 8870 Елена (бухг) | S11: ЗУ на 49 лет. ЦН ЗУ - Пашня.
A12: 5 | C12: Енбекшиказахский район | D12: ТОО «Kasym ASES», Рахатский с/о | E12: Завод по переработке куриных лап | F12: Проблемный | G12: 200 | I12: 1221 | K12: 1221 | M12: 2026 г. | N12: 2027 г. | O12: 3 | P12: 15 000 тонн/год | Q12: Произведена смена целевого назначения земельного участка на промышленное использование, на стадии получения государственного акта. Имеется частичная инфраструктура: получены технические условия по электроснабжению, подведено освещение, водоснабжение обеспечено через скважину, газоснабжение отсутствует, подъездной путь требует отсыпки. В связи с планируемой сменой учредителя (вхождение гражданина Турции с соответствующим опытом и инвестициями) и руководителя ТОО в июле текущего года, работы по подаче заявки на АПЗ не проводились. | R12: Жолдыбай Есентай руководитель и учредитель, представитель Адильбек Аргинбаев 8 778 358 9621 | S12: ЦН ЗУ - пастбища
A13: 6 | C13: Енбекшиказахский район | D13: ТОО "ПОМОНА" | E13: Строительство и эксплуатация систем влагосберегающих технологий для выращивание кукурузы на зерно | F13: Инвестиционные проекты реализуемые по программе развития растениеводства. | H13: Растениевод | K13: 361.8 | P13: 794 тонны в год | Q13: Ранее несоответствующее договору оборудование возвращено поставщику. На текущий момент приобретено новое оборудование, которое находится на складе поставщика. Поставка на объект и завершение монтажных работ запланированы на август 2026 года. | R13: Аяпбергенов Бауржан Болатович
A14: 7 | C14: Енбекшиказахский район | D14: ТОО "Revival of apples" | E14: Строительство и эксплуатация систем влагосберегающих технологий для выращивание кукурузы на зерно | F14: Инвестиционные проекты реализуемые по программе развития растениеводства. | H14: Растениевод | K14: 520 | P14: 1 253 тонн в год | Q14: На площадку реализации проекта поставлена сельскохозяйственная техника, включая разбрасыватели жидкого и твердого навоза, а также кормораздатчики. Ранее несоответствующее договору оборудование возвращено поставщику. Новое оборудование приобретено и находится на складе поставщика, его поставка и монтаж запланированы на август 2026 года. | R14: Молдаш Әсел
A15: 8 | C15: Жамбылский район | D15: TOO «DARIA Company», Шолаккаргалинский с/о | E15: Тепличный комплекс | F15: Проблемный | G15: 70 | I15: 15000 | K15: 15000 | L15: 15000 | M15: 2027 г. | O15: 15 | P15: 3 тыс тонн год | Q15: В связи с несоответствием ранее полученных технических условий по электроснабжению и газоснабжению требованиям проекта проводится перепроектирование линии электропередачи (срок завершения — до 15.06.2026 г.). После получения обновлённых решений проект будет направлен на государственную экспертизу. Финансирование планируется через АО «Банк Развития Казахстана» (БРК). Работы в настоящее время не ведутся. В связи с неактивностью инвестора предлагается вынести на заседание РКС по отзыву ЗУ. | R15: Руководитель - Мацыгин Дмитрий Вениаминович, 8 777 229 5000 Маргулан; Акмарал 8 747 701 87 74 | S15: ЗУ на 3 года. ЦН ЗУ - пашня орошаемая
A16: 9 | C16: Карасайский район | D16: СПК «Жетысу» | E16: Молочно товарная ферма | F16: Реализуемые проекты, по линии кредитования АПК по опыту СКО | H16: СКО | K16: 994 | L16: 994 | Q16: Заемщику неоднократно разъяснялась необходимость своевременного освоения заемных средств. 17 июля 2025 года заключен договор с ТОО «PANAGRO SERVICE» на приобретение доильно-молочного блока с доильным залом стоимостью 374 000 000 тенге, оплата произведена 21 июля 2025 года. 30 июля 2025 года прокуратурой Алматинской области внесено представление в связи с нецелевым использованием займа и размещением средств на депозитных счетах. В результате проведенной Поверенным (агентом) работы 25 сентября 2025 года СПК «Жетысу» возвратило часть займа в размере 620 102 785 тенге. По оставшейся сумме займа (374 000 000 тенге) и взысканию штрафа Поверенным (агентом) подан иск в суд. Решением суда первой инстанции от 26 декабря 2025 года с СПК «Жетысу» взысканы сумма займа и штраф в размере 248 525 696 тенге. 17 марта 2026 года апелляционная инстанция отменила данное решение. 2 апреля 2026 года подана кассационная жалоба. Ожидается назначение судебного заседания. | R16: Исагулов Жанат
A17: 10 | C17: г.Конаев | D17: ТОО «AXIS Holding», Шенгельдинский с/о, уч. кв. 254 (уч.364 А) | E17: Строительство МТФ на 12 000 КРС, дойное стадо 6 000 КРС. Также строительство цехов по переработке молока и выпуску молочной продукции. | F17: Проблемный | G17: 400 | I17: 121580 | K17: 121580 | M17: 2030 г. | O17: 1340 | P17: 55 тыс.тонн в год | Q17: По факту земельный участок был получен в январе текущего года, после чего начались работы по подготовке проектной документации. Ориентировочный срок завершения разработки проекта — конец июля текущего года. Вместе с тем в ходе отбора и анализа проб воды были получены результаты, свидетельствующие о повышенном содержании солей. Использование такой воды может привести к снижению удоев молока, а также потребует строительства системы водоочистки, что влечет за собой удорожание проекта. В настоящее время рассматривается вопрос о выделении дополнительного земельного участка площадью 1000 кв. м вблизи Капшагайского водохранилища для обеспечения возможности использования воды из данного источника. В связи с изложенным сроки завершения подготовки проектной документации могут быть перенесены. | R17: Василий Филимонов +49 162 7018421 | S17: ЗУ на 3 года. ЦН ЗУ - прочие земли
A18: 11 | C18: г. Конаев | D18: ТОО «KazGelatin» | E18: Строительство завода по производству пищевого желатина | F18: Проблемный | G18: 100 | I18: 29900 | K18: 29900 | M18: 2027 г. | O18: 44.6 | P18: 10 тыс. тонн | Q18: Ведутся работы по поиску ЗУ для наносной станции | S18: нет
A19: 12 | C19: Талгарский район | D19: ИП Гульмир | E19: Создание УЗВ | G19: 6 | H19: собственные средства | I19: 350 | K19: 350 | M19: 2025 | P19: 80 тонн форели | Q19: 1. На сегодняшний день в рамках проекта по выращиванию форели установлено 6 бассейнов объёмом по 3 тонны каждый, проведено зарыбление рыбопосадочным материалом форели, осуществляется инкубация. На участке имеется пруд, используемый для выращивания рыбы. Ведётся строительство 6 бассейнов под открытым небом ёмкостью по 4 тонны каждый. 2. К хозяйству подведено электроснабжение, функционирует собственная подстанция, обеспечивающая стабильную работу оборудования. 3. Степень готовности проекта составляет около 80% от общего объёма строительно-монтажных работ. Параллельно осуществляется оформление всех необходимых документов и разрешений для полного запуска производства и реализации продукции. 4. Проект реализуется за счёт собственных средств инициатора — индивидуального предпринимателя «Гульмир». На текущий момент инвестировано 250 млн тенге. Для выхода на полную производственную мощность планируется подача заявки на льготный кредит в размере 100 млн тенге под 2,5% годовых. Нужны средства в размере 100 млн. тенге для полного запуска производства
A20: 13 | C20: Илийский район | D20: ИП "Бақыт" | E20: Создание садкового рыбоводного хозяйства | H20: собственные средства | I20: 500 | K20: 500 | M20: 2025 | Q20: Выращивание карпа и форели в садковом хозяйстве, изготовление садков для выращивания аквакультур. Нужно получить право долгосрочной аренды на земельный участок с прудом № 10, занимают площадь без разрешительных документов
A21: 14 | C21: г. Алатау | D21: ИП "Алатау Балық" | E21: Создание садкового рыбоводного хозяйства | G21: 10 | H21: собственные средства | I21: 500 | K21: 500 | M21: 2025 | P21: 500 тонн карповые | Q21: 1. В 2025 году к участку проведено электричество, установлена собственная подстанция и проложена грунтовая дорога. 2. Установлено 4 садка и проведено зарыбление 6 000 шт. рыбопосадочного материала карпа. 3. Хозяйство находится на этапе выращивания с регулярным контролем состояния рыбы, качества воды и режима кормления. 4. Ведутся работы по корректировке участка водного стекла, а также оформление и регистрация всех необходимых документов и разрешений. 5. До конца 2025 года планируется инвестировать дополнительно 100 млн тг и подать заявку на льготный кредит под 2,5 % на 500 млн тг. 6. Собственник планирует в любом случае реализовать проект до 2030 года; срок выхода на полную мощность зависит от результатов заявки на кредит: в случае положительного решения все 70 садков будут установлены уже в 2026 году. Нужны средства в размере 500 млн. тенге для полного запуска

Sheet Прост и исключенные
D2: кол | E2: сумма | F2: Раб. места
C3: Прост и исключенные | D3: 6 | E3: 51511 | F3: 910
A6: № | B6: № | C6: Район | D6: Наименование компании | E6: Наименование проекта | F6: Стадия проекта | G6: Раб. Места | H6: Финансирование | I6: Стоимость, млн. тенге | M6: Ввод объекта по РКС | N6: Ввод объекта по факту | O6: Площадь земельного участка, га | P6: Мощность проекта и производительность | Q6: Текущий статус | R6: ФИО руководителя, контакты | S6: Меры господдержки
H7: Собственные, АКК/БРК, Растениевод, СКО | I7: Всего по РКС | J7: Вне РКС | K7: Актуализир. сумма | L7: в т.ч. заемные
A8: 20 | B8: 1 | C8: Енбекшиказахский район | D8: ИП «Тұржан Дәулетхан Мәжитұлы» | E8: Строительство молочно товарной фермы | F8: Реализуемые проекты, по линии кредитования АПК по опыту СКО | H8: СКО | K8: 2000 | L8: 2000 | P8: 612 голов, 2700 тонн в год | Q8: Строительство МТФ завершено, оборудование доильного зала установлено, ожидается пусконаладка, скот не поставлен, но оплата произведена. В связи с неисполнением обязательств, АО "СПК Конаев" подал исковое заявление о погашении просроченной задолженности. | R8: Маметов Марат
A9: 21 | B9: 1 | C9: Енбекшиказахский район | D9: АО «Агропромышленная компания Адал» | E9: Современная молочно-товарная ферма | F9: Реализован | H9: СКО | K9: 1833.8 | L9: 1833.8 | P9: 2371 голов, 11160 тонн в год | Q9: Строительство дополнительного корпуса МТФ и нового доильного зала завершено, монтаж оборудования коровника и доильного зала завершено. | R9: Смаилов Серик
A10: 59 | B10: 1 | C10: г.Конаев | D10: ТОО «Sofood Kaz» | E10: Строительство завода по производству сыра | F10: Реализуемые проекты, прошедшие РКС | G10: 460 | I10: 35291 | K10: 35291 | L10: 28233 | M10: 2027 г. | O10: 31.8 | P10: 100 тонн в день | Q10: Завершается ограждение ЗУ - 31 га по всему периметру. На период СМР временно подключены э/э, водоснабжения, завершён монтаж временного дорожного покрытия. Ведется СМР складских помещений на 10 тыс кв.м, (ввод 10.2026г.). Подведение инженерной и коммунальной инфраструктуры (ИКИ) планируется за счет местного бюджета. Бюджетная заявка будет вынесена на очередное уточнение бюджета. В настоящее время разрабатывается проектно-сметная документация, ориентировочные сроки получения ПСД первая декада июля и получение государственной экспертизы вторая декада сентября,так как ориентировочные сроки гос. экспертизы 45 дней. В связи с чем, окончательная стоимость будет определена после её завершения. | R10: Аманкосов Курмангали Жандосович 87021324043 , Рауан +7 (707) 837 09 11 | S10: ЗУ на 3 года. ЦН ЗУ - прочие земли
A11: 66 | B11: 1 | C11: г.Алатау | D11: ТОО «Zhetysu Koy», | E11: Строительство мясокомбината по докорму, убою и глубокой переработке МРС | F11: Реализуемые проекты, прошедшие РКС | G11: 450 | I11: 12386.2 | K11: 12386.2 | M11: 2027 г. | N11: 2029 г. | O11: 24 | P11: Баранина: 15 т.тн в год-1 этап; 30 т.тн в год - 2 этап | Q11: Проект строительства мясокомбината разработан и готов к реализации, однако его реализация приостановлена до решения вопроса обеспечения объекта канализационной инфраструктурой. По информации инвестора, ранее был разработан и получен положительный результат ГЭ проекта КОС для земельного участка площадью 70 га, который впоследствии был сокращен до 24 га. Вопрос строительства канализационной системы до настоящего времени не решен и является основным сдерживающим фактором проекта. После получения подтверждения о строительстве канализационной инфраструктуры и сроках ее ввода проект будет возобновлен. Финансовые ресурсы для реализации проекта имеются. В связи с неактивностью инвестора предлагается вынести на заседание РКС по отзыву ЗУ. | R11: Плотников Олег Геннадьевич +7 701 722 3319 | S11: Подведение недостающей ИКИ. ЦН ЗУ - пастбище.
A12: 74 | B12: 1 | D12: ТОО «BELES AGRO KZ»
A13: 75 | B13: 1 | D13: ТОО «AGRO Bionics»

Sheet РКС

Sheet СВОД
A2: Перечень проектов АПК, прошедших РКС за 2023-2025 годы
A5: № | B5: Район/ Город | C5: Всего проектов | E5: Реализуемые проекты | I5: Отозванные проекты
C6: Кол-во | D6: Сумма | E6: Кол-во | F6: Рабочие места | G6: Стоимость, млн. тенге | I6: Кол-во | J6: Рабочие места | K6: Стоимость, млн. тенге
G7: Всего | H7: в т.ч. заемные
B8: Всего | C8: =SUM(C9:C18) -> 39 | D8: =SUM(D9:D18) -> #REF! | E8: =SUM(E9:E18) -> 28 | F8: =SUM(F9:F18) -> 3969 | G8: =SUM(G9:G18) -> 428389.93 | H8: =SUM(H11:H17) -> 104500 | I8: =SUM(I9:I18) -> 11 | J8: =SUM(J9:J18) -> #REF! | K8: =SUM(K9:K18) -> #REF!
A9: 1 | B9: Конаев | C9: =SUM(E9+I9) -> 5 | D9: =SUM(G9+K9) -> #REF! | E9: 4 | F9: =SUM(Реализация!F14+Реализация!F27+Реализация!F31+Реализация!F37) -> 1518 | G9: =SUM(Реализация!G14+Реализация!G27+Реализация!G31+Реализация!G37) -> 168781 | H9: =SUM(Реализация!H14+Реализация!H27+Реализация!H31+Реализация!H37) -> 23400 | I9: 1 | J9: =SUM(#REF!) -> #REF! | K9: =SUM(#REF!) -> #REF!
A10: 2 | B10: Уйгурский | C10: =SUM(E10+I10) -> 5 | D10: =SUM(G10+K10) -> #REF! | E10: 1 | F10: =SUM(Реализация!F19) -> 50 | G10: =SUM(Реализация!G19) -> 1000 | H10: =SUM(Реализация!H19) -> 0 | I10: 4 | J10: =SUM(#REF!+#REF!+#REF!+#REF!) -> #REF! | K10: =SUM(#REF!+#REF!+#REF!+#REF!) -> #REF!
A11: 3 | B11: Алатау | C11: =SUM(E11+I11) -> 4 | D11: =SUM(G11+K11) -> 118589.2 | E11: 4 | F11: =SUM(Реализация!F15+Реализация!F16+Реализация!F17+Реализация!F18) -> 949 | G11: =SUM(Реализация!G15+Реализация!G16+Реализация!G17+Реализация!G18) -> 118589.2 | H11: =SUM(Реализация!H15+Реализация!H16+Реализация!H17+Реализация!H18) -> 81000
A12: 4 | B12: Енбекшиказахский | C12: =SUM(E12+I12) -> 13 | D12: =SUM(G12+K12) -> #REF! | E12: 9 | F12: =SUM(Реализация!F20+Реализация!F21+Реализация!F25+Реализация!F26+Реализация!F29+Реализация!F33+Реализация!F34+Реализация!F35+Реализация!F36) -> 704 | G12: =SUM(Реализация!G20+Реализация!G21+Реализация!G25+Реализация!G26+Реализация!G29+Реализация!G33+Реализация!G34+Реализация!G35+Реализация!G36) -> 77062.933 | H12: =SUM(Реализация!H20+Реализация!H21+Реализация!H25+Реализация!H26+Реализация!H29+Реализация!H33+Реализация!H34+Реализация!H35+Реализация!H36) -> 8500 | I12: 4 | J12: =SUM(#REF!+#REF!+#REF!+#REF!) -> #REF! | K12: =SUM(#REF!+#REF!+#REF!+#REF!) -> #REF!
A13: 5 | B13: Илийский | C13: =SUM(E13+I13) -> 2 | D13: =SUM(G13+K13) -> 5550 | E13: 2 | F13: =SUM(Реализация!F22+Реализация!F28) -> 90 | G13: =SUM(Реализация!G22+Реализация!G28) -> 5550 | H13: =SUM(Реализация!H22+Реализация!H28) -> 0
A14: 6 | B14: Карасайский | C14: =SUM(E14+I14) -> 1 | D14: =SUM(G14+K14) -> 15800 | E14: 1 | F14: =SUM(Реализация!F32) -> 250 | G14: =SUM(Реализация!G32) -> 15800 | H14: =SUM(Реализация!H32) -> 0
A15: 7 | B15: Кегенский | C15: =SUM(E15+I15) -> 1 | D15: =SUM(G15+K15) -> #REF! | I15: 1 | J15: =SUM(#REF!) -> #REF! | K15: =SUM(#REF!) -> #REF!
A16: 8 | B16: Балхашский | C16: =SUM(E16+I16) -> 3 | D16: =SUM(G16+K16) -> 4106.8 | E16: 3 | F16: =SUM(Реализация!F13+Реализация!F38+Реализация!F39) -> 153 | G16: =SUM(Реализация!G13+Реализация!G38+Реализация!G39) -> 4106.8 | H16: =SUM(Реализация!H13+Реализация!H38+Реализация!H39) -> 0
A17: 9 | B17: Жамбылский | C17: =SUM(E17+I17) -> 3 | D17: =SUM(G17+K17) -> #REF! | E17: 2 | F17: =SUM(Реализация!F23+Реализация!F40) -> 90 | G17: =SUM(Реализация!G23+Реализация!G40) -> 15750 | H17: =SUM(Реализация!H23+Реализация!H40) -> 15000 | I17: 1 | J17: =SUM(#REF!) -> #REF! | K17: =SUM(#REF!) -> #REF!
A18: 10 | B18: Талгарский | C18: =SUM(E18+I18) -> 2 | D18: =SUM(G18+K18) -> 21750 | E18: 2 | F18: =SUM(Реализация!F24+Реализация!F30) -> 165 | G18: =SUM(Реализация!G24+Реализация!G30) -> 21750 | H18: =SUM(Реализация!H24+Реализация!H30) -> 0

Sheet Реализация
A2: Перечень реализуемых проектов АПК, прошедших РКС за 2023-2025 годы | N2: Годы | O2: кол-во | P2: реализ | R2: кол-во | S2: отказ | U2: места | V2: ВСЕГО | W2: кол-во
N3: Всего | O3: =SUM(O4:O7) -> 28 | P3: =SUM(P4:P7) -> 3969 | Q3: =SUM(Q4:Q7) -> 428389.93 | R3: =SUM(R4:R7) -> 11 | S3: =SUM(S4:S7) -> #REF! | T3: =SUM(T4:T7) -> #REF! | U3: =P3+S3 -> #REF! | V3: =Q3+T3 -> #REF! | W3: =SUM(W4:W7) -> 39
B4: Всего - 28, из них: | N4: 2022 | O4: 1 | P4: =F15 -> 99 | Q4: =G15 -> 6503 | R4: 1 | S4: =#REF! -> #REF! | T4: =#REF! -> #REF! | U4: =P4+S4 -> #REF! | V4: =Q4+T4 -> #REF! | W4: =SUM(O4+R4) -> 2
B5: реализовано - 2, на стадии реализации -26 | N5: 2023 | O5: 5 | P5: =F13+F14+F16+F17+F18 -> 1400 | Q5: =G13+G14+G16+G17+G18 -> 122273 | R5: 4 | S5: =#REF! -> #REF! | T5: =#REF! -> #REF! | U5: =P5+S5 -> #REF! | V5: =Q5+T5 -> #REF! | W5: =SUM(O5+R5) -> 9
B6: Ввод: в 2026 г - 6 проектов на 105,2 млрд.тенге; | N6: 2024 | O6: 7 | P6: =F19+F20+F21+F22+F23+F24+F25 -> 478 | Q6: =G19+G20+G21+G22+G23+G24+G25 -> 45000 | R6: 4 | S6: =#REF! -> #REF! | T6: =#REF! -> #REF! | U6: =P6+S6 -> #REF! | V6: =Q6+T6 -> #REF! | W6: =SUM(O6+R6) -> 11
B7: в 2027 г - 11 проектов на 110 млрд.тенге; | N7: 2025 | O7: 15 | P7: =F26+F27+F28+F29+F30+F31+F32+F33+F34+F35+F36+F37+F38+F39+F40 -> 1992 | Q7: =G26+G27+G28+G29+G30+G31+G32+G33+G34+G35+G36+G37+G38+G39+G40 -> 254613.93 | R7: 2 | S7: =#REF! -> #REF! | T7: =#REF! -> #REF! | U7: =P7+S7 -> #REF! | V7: =Q7+T7 -> #REF! | W7: =SUM(O7+R7) -> 17
B8: в 2028-2034гг - 9 проектов на 213,2 млрд.тенге. | P8: =SUM(F16+F17+F18) -> 850 | Q8: =SUM(G16+G17+G18) -> 112086.2
A10: № | B10: Дата РКС | C10: Район/Город | D10: Наименование компании | E10: Наименование проекта | F10: Рабочие места | G10: Стоимость, млн. тенге | I10: Ввод объекта | J10: Текущий статус | K10: Площадь земельного участка, га | L10: Меры господдержки | N10: ввод | P10: 2026 | R10: 2027 | T10: 2028-2034
G11: Всего | H11: в т.ч. заемные
B12: Всего | F12: =SUM(F13:F40) -> 3969 | G12: =SUM(G13:G40) -> 428389.93 | H12: =SUM(H13:H40) -> 127900 | K12: =SUM(K13:K40) -> 16114.264 | P12: =F18+F20+F21++F28+F36+F40 -> 708 | Q12: =G18+G20+G21++G28+G36+G40 -> 105171 | R12: =F16+F17+F23+F24+F26+F29+F31+F32+F35+F38+F39 -> 1738 | S12: =G16+G17+G23+G24+G26+G29+G31+G32+G35+G38+G39 -> 109973.8 | T12: =F12-P12-R12 -> 1523 | U12: =G12-Q12-S12 -> 213245.13
A13: 1 | B13: 44930 | C13: Балхашский | D13: ТОО «Биокарбон» - реализован | E13: Строительство наружных сетей газоснабжение производственной базы переработки рисовой шелухи в производство древесноугольных брикетов | F13: 50 | G13: 386.8 | I13: 2025 г. | K13: 0.9936 | L13: Подведение недостающей инфраструктуры | O13: =SUM(F12-F13-F14) -> 3419 | P13: =SUM(G12-G13-G14) -> 418203.13
A14: 2 | B14: 44930 | C14: Конаев | D14: ТОО «Оспанова Девелопмент» - реализован | E14: Строительство рыбопромышленного комплекса, трасса Алматы-Конаев (1 этап) | F14: 500 | G14: 9800 | H14: 300 | I14: 2023 г. | K14: 27 | L14: Подведение недостающей инфраструктуры | O14: =SUM(F13:F14) -> 550 | P14: =SUM(G13:G14) -> 10186.8
A15: 3 | B15: 44785 | C15: Алатау | D15: ТОО «Yukos Group» | E15: Строительство тепличного комплекса с целью выращивания томатов | F15: 99 | G15: 6503 | I15: 2028 г. | J15: Ген план АРНА | K15: 5 | L15: Земельный участок
A16: 4 | B16: 45048 | C16: Алатау | D16: ТОО «Молочная Долина» | E16: Строительство молочно-товарной фермы на 1200 голов | F16: 100 | G16: 18700 | H16: 10000 | I16: 2027 г. | J16: Проект готовится к направлению на ГЭ | K16: 1300 | L16: Земельный участок
A17: 5 | B17: 45083 | C17: Алатау | D17: ТОО «Zhetysu Koy» | E17: Строительство мясокомбината по докорму, убою и глубокой переработке МРС | F17: 450 | G17: 12386.2 | I17: 2027 г. | J17: Подготовка пакета документов | K17: 24 | L17: Подведение недостающей инфраструктуры
A18: 6 | B18: 45240 | C18: Алатау | D18: ТОО «ПепсиКо ЦА» | E18: Завод по производству соленых закусок | F18: 300 | G18: 81000 | H18: 71000 | I18: 2026 г. | J18: Ведутся СМР | K18: 26.47 | L18: Земельный участок
A19: 7 | B19: 45392 | C19: Уйгурский | D19: ТОО «Rancho Hampshire» | E19: Организация производственной базы сельхозназначения (Разведение английской породы овец Гемпшир и выращивание кукурузы, люцерны и разнотравья) | F19: 50 | G19: 1000 | I19: 2028 г. | J19: Ведутся СМР | K19: 797 | L19: Земельный участок
A20: 8 | B20: 45537 | C20: Енбекшиказахский | D20: ТОО «Kazakhstan Central Asia Industrial Company., Ltd» | E20: Переработка биологических отходов и производство органических, экологически чистых удобрений животного происхождения | F20: 30 | G20: 7200 | I20: 2026 г. | J20: Ведутся СМР | K20: 10
A21: 9 | B21: 45558 | C21: Енбекшиказахский | D21: ТОО «Qazaq Global Food JV» | E21: Строительство завода по переработке фруктов и овощей (производству концентратов фруктовых соков, овощных и фруктовых пюре с инфраструктурой хранения сортировки и упаковки фруктов) | F21: 128 | G21: 10000 | H21: 7000 | I21: 2026 г. | J21: Ведутся СМР | K21: 30 | L21: Земельный участок
A22: 10 | B22: 45568 | C22: Илийский | D22: ТОО «Компания «Сары Булак» | E22: По переработке куриного помёта в органические удобрения | F22: 60 | G22: 550 | J22: Ведутся СМР | K22: 6 | L22: Земельный участок
A23: 11 | B23: 45638 | C23: Жамбылский | D23: TOO «DARIA Company» | E23: Тепличный комплекс | F23: 70 | G23: 15000 | H23: 15000 | I23: 2027 г. | J23: На стадии перепроектирования | K23: 15 | L23: Земельный участок
A24: 12 | B24: 45652 | C24: Талгарский | D24: СПК «Племзавод «Алматы» | E24: Развитие овцеводства породы Иль-Де-Франс в Жетысу | F24: 100 | G24: 750 | I24: 2027 г. | J24: Реализуемый | K24: 2000 | L24: Земельный участок
A25: 13 | B25: 45331 | C25: Енбекшиказахский, ИЗ «Шелек» | D25: ТОО «AGROFINANCE» | E25: Строительство ультрасовременного фруктохранилища в Алматинской области | F25: 40 | G25: 10500 | I25: 2028 г. | J25: Ожидает подведения инфраструктуры на ИЗ «Шелек» | K25: 5 | L25: Размещение ИЗ «Шелек»
A26: 14 | B26: 45687 | C26: Енбекшиказахский | D26: TOО «Тепличный агропромышленный комплекс Синтай» | E26: Тепличный агропромышленный комплекс "Xingtai" в Алматинской области | F26: 100 | G26: 3250 | I26: 2027 г. | J26: Изменение целевого назначения земельного участка | K26: 50 | L26: Земельный участок
A27: 15 | B27: 45687 | C27: г. Конаев | D27: ТОО «AXIS Holding» | E27: Строительство МТФ | F27: 400 | G27: 121580 | I27: 2030 г. | J27: Поиск ЗУ для насосной станции | K27: 1340 | L27: Земельный участок
A28: 16 | B28: 45687 | C28: Илийский | D28: ТОО «Alfalfa» | E28: Выращивание люцерны | F28: 30 | G28: 5000 | I28: 2026 г. | J28: Ожидание финансирования | K28: 2500 | L28: Подведение недостающей инфраструктуры
A29: 17 | B29: 45715 | C29: Енбекшиказахский | D29: ТОО «Батал Агро» | E29: Производство семян кукурузы родительских форм | F29: 85 | G29: 3500 | H29: 1500 | I29: 2027 г. | J29: Судебный процесс касательно ЗУ | K29: 94 | L29: Земельный участок
A30: 18 | B30: 45715 | C30: Талгарский, ИЗ «Кайрат» | D30: ТОО «MES Story Invest» | E30: Строительство завода по производству элеваторов и стальных силосов | F30: 65 | G30: 21000 | I30: 2028 г. | J30: На стадии разработки ПСД | K30: 10.1 | L30: Размещение ИЗ «Кайрат»
A31: 19 | B31: 45723 | C31: г. Конаев | D31: ТОО «Sofood Kaz» | E31: Строительство завода по производству сыра | F31: 460 | G31: 35291 | H31: 23100 | I31: 2027 г. | J31: Ведутся СМР | K31: 31.8 | L31: Земельный участок
A32: 20 | B32: 45757 | C32: Карасайский | D32: ТОО «Жигалма» (Caspian Beverage Holdings) | E32: Производство безалкогольных напитков и минеральных вод | F32: 250 | G32: 15800 | I32: 2027 г. | J32: Подготовка документации | K32: 10 | L32: Земельный участок
A33: 21 | B33: 45771 | C33: Енбекшиказахский | D33: ТОО «Дусан Инжиниринг» | E33: Организация молочно-товарной фермы | F33: 50 | G33: 31840 | I33: 2034 г. | J33: Подготовительные работы | K33: 84 | L33: Земельный участок
A34: 22 | B34: 45827 | C34: Енбекшиказахский | D34: ТОО «QazEcoDan» | E34: Строительство комплекса по приемке, очистке, сушке и хранению зерновых и масленичных культур, производству комбинированных кормов | F34: 51 | G34: 7975.333 | I34: 2033 г. | J34: Ведутся СМР | K34: 9.6 | L34: Земельный участок
A35: 23 | B35: 45827 | C35: Енбекшиказахский | D35: ТОО «Мың жылқы шаруа қожалығы» | E35: Строительство и организация деятельности конефермы | F35: 20 | G35: 1576.6 | I35: 2027 г. | J35: Подготовка к СМР | K35: 4457.7 | L35: Земельный участок
A36: 24 | B36: 45841 | C36: Енбекшиказахский | D36: ТОО «Kasym ASES» | E36: Завод по переработке куриных лап | F36: 200 | G36: 1221 | I36: 2026 г. | J36: СМР завершены, акта ввода на стадии выдачи | K36: 3 | L36: Земельный участок
A37: 25 | B37: 45890 | C37: г. Конаев | D37: ТОО «Asian International Trading Company» | E37: Строительство завода по производству комбикорма из плющенной кукурузы | F37: 158 | G37: 2110 | I37: 2029 г. | J37: Земляные работы | K37: 20 | L37: Земельный участок
A38: 26 | B38: 45925 | C38: Балхашский | D38: ТОО «Тайда животноводство» | E38: Строительство агропромышленного комплекса по производству яиц | F38: 68 | G38: 3120 | I38: 2027 г. | J38: На стадии разработки ПСД | K38: 50 | L38: Земельный участок
A39: 27 | B39: 45967 | C39: Балхашский | D39: ТОО «Баканас рис» | E39: Выращивание риса в Алматинской области | F39: 35 | G39: 600 | I39: 2027 г. | J39: Земляные работы | K39: 707.6 | L39: Земельный участок
A40: 28 | B40: 45988 | C40: Жамбылский | D40: ТОО «Кок Тениз К» | E40: Расширение мощностей по переработке кукурузы с 20 000 до 50 000 тонн в год | F40: 20 | G40: 750 | I40: 2026 г. | J40: Подготовка к СМР | K40: 2500 | L40: Земельный участок
